{"brand":"Foton","model":"Midi","generation":{"name":"","years":"2007 – 2014","url":"https://auto.ru/catalog/cars/foton/midi/20346602/20468302/"},"complectation":{"name":"Модификация 1.3 MT","specification":[{"head":"Основные","name":"Объем","value":"1.3 л"},{"head":"Основные","name":"Мощность","value":"85 л.с."},{"head":"Основные","name":"Коробка","value":"механика"},{"head":"Основные","name":"Тип двигателя","value":"бензин"},{"head":"Основные","name":"Топливо","value":"АИ-95"},{"head":"Основные","name":"Привод","value":"передний"},{"head":"Общая информация","name":"Страна марки","value":"Китай"},{"head":"Общая информация","name":"Класс автомобиля","value":"M"},{"head":"Общая информация","name":"Количество дверей","value":"5"},{"head":"Общая информация","name":"Количество мест","value":"5"},{"head":"Размеры, мм","name":"Длина","value":"4288"},{"head":"Размеры, мм","name":"Ширина","value":"1725"},{"head":"Размеры, мм","name":"Высота","value":"1728"},{"head":"Размеры, мм","name":"Колёсная база","value":"2700"},{"head":"Размеры, мм","name":"Клиренс","value":"150"},{"head":"Объём и масса","name":"Объем багажника мин/макс, л","value":"-"},{"head":"Трансмиссия","name":"Коробка передач","value":"механика"},{"head":"Трансмиссия","name":"Количество передач","value":"5"},{"head":"Трансмиссия","name":"Тип привода","value":"передний"},{"head":"Подвеска и тормоза","name":"Тип передней подвески","value":"независимая, пружинная"},{"head":"Подвеска и тормоза","name":"Передние тормоза","value":"дисковые"},{"head":"Подвеска и тормоза","name":"Задние тормоза","value":"барабанные"},{"head":"Эксплуатационные показатели","name":"Марка топлива","value":"АИ-95"},{"head":"Двигатель","name":"Тип двигателя","value":"бензин"},{"head":"Двигатель","name":"Объем двигателя, см³","value":"1298"},{"head":"Двигатель","name":"Тип наддува","value":"нет"},{"head":"Двигатель","name":"Максимальная мощность, л.с./кВт при об/мин","value":"85 / 63 при 6000"},{"head":"Двигатель","name":"Максимальный крутящий момент, Н*м при об/мин","value":"108 при 4500"},{"head":"Двигатель","name":"Расположение цилиндров","value":"рядное"},{"head":"Двигатель","name":"Количество цилиндров","value":"4"},{"head":"Двигатель","name":"Число клапанов на цилиндр","value":"4"},{"head":"Двигатель","name":"Система питания двигателя","value":"распределенный впрыск (многоточечный)"},{"head":"Двигатель","name":"Диаметр цилиндра и ход поршня, мм","value":"-"}],"url":"https://auto.ru/catalog/cars/foton/midi/20346602/20468302/specifications/20468302__20468333/"}}
{"brand":"Foton","model":"Midi","generation":{"name":"","years":"2007 – 2014","url":"https://auto.ru/catalog/cars/foton/midi/20346602/20468302/"},"complectation":{"name":"Модификация 1.5 MT","specification":[{"head":"Основные","name":"Объем","value":"1.5 л"},{"head":"Основные","name":"Мощность","value":"103 л.с."},{"head":"Основные","name":"Коробка","value":"механика"},{"head":"Основные","name":"Тип двигателя","value":"бензин"},{"head":"Основные","name":"Топливо","value":"АИ-95"},{"head":"Основные","name":"Привод","value":"передний"},{"head":"Общая информация","name":"Страна марки","value":"Китай"},{"head":"Общая информация","name":"Класс автомобиля","value":"M"},{"head":"Общая информация","name":"Количество дверей","value":"5"},{"head":"Общая информация","name":"Количество мест","value":"5"},{"head":"Размеры, мм","name":"Длина","value":"4288"},{"head":"Размеры, мм","name":"Ширина","value":"1725"},{"head":"Размеры, мм","name":"Высота","value":"1728"},{"head":"Размеры, мм","name":"Колёсная база","value":"2700"},{"head":"Размеры, мм","name":"Клиренс","value":"150"},{"head":"Объём и масса","name":"Объем багажника мин/макс, л","value":"-"},{"head":"Трансмиссия","name":"Коробка передач","value":"механика"},{"head":"Трансмиссия","name":"Количество передач","value":"5"},{"head":"Трансмиссия","name":"Тип привода","value":"передний"},{"head":"Подвеска и тормоза","name":"Тип передней подвески","value":"независимая, пружинная"},{"head":"Подвеска и тормоза","name":"Передние тормоза","value":"дисковые"},{"head":"Подвеска и тормоза","name":"Задние тормоза","value":"барабанные"},{"head":"Эксплуатационные показатели","name":"Марка топлива","value":"АИ-95"},{"head":"Двигатель","name":"Тип двигателя","value":"бензин"},{"head":"Двигатель","name":"Объем двигателя, см³","value":"1499"},{"head":"Двигатель","name":"Тип наддува","value":"нет"},{"head":"Двигатель","name":"Максимальная мощность, л.с./кВт при об/мин","value":"103 / 76 при 6000"},{"head":"Двигатель","name":"Максимальный крутящий момент, Н*м при об/мин","value":"130 "},{"head":"Двигатель","name":"Расположение цилиндров","value":"рядное"},{"head":"Двигатель","name":"Количество цилиндров","value":"4"},{"head":"Двигатель","name":"Число клапанов на цилиндр","value":"4"},{"head":"Двигатель","name":"Система питания двигателя","value":"распределенный впрыск (многоточечный)"},{"head":"Двигатель","name":"Диаметр цилиндра и ход поршня, мм","value":"-"}],"url":"https://auto.ru/catalog/cars/foton/midi/20346602/20468302/specifications/20468302__20468385/"}}
{"brand":"Foton","model":"Midi","generation":{"name":"","years":"2007 – 2014","url":"https://auto.ru/catalog/cars/foton/midi/20346602/20468302/"},"complectation":{"name":"Модификация 1.6 MT","specification":[{"head":"Основные","name":"Объем","value":"1.6 л"},{"head":"Основные","name":"Мощность","value":"101 л.с."},{"head":"Основные","name":"Коробка","value":"механика"},{"head":"Основные","name":"Тип двигателя","value":"бензин"},{"head":"Основные","name":"Топливо","value":"АИ-95"},{"head":"Основные","name":"Привод","value":"передний"},{"head":"Общая информация","name":"Страна марки","value":"Китай"},{"head":"Общая информация","name":"Класс автомобиля","value":"M"},{"head":"Общая информация","name":"Количество дверей","value":"5"},{"head":"Общая информация","name":"Количество мест","value":"5"},{"head":"Размеры, мм","name":"Длина","value":"4288"},{"head":"Размеры, мм","name":"Ширина","value":"1725"},{"head":"Размеры, мм","name":"Высота","value":"1728"},{"head":"Размеры, мм","name":"Колёсная база","value":"2700"},{"head":"Размеры, мм","name":"Клиренс","value":"150"},{"head":"Объём и масса","name":"Объем багажника мин/макс, л","value":"-"},{"head":"Трансмиссия","name":"Коробка передач","value":"механика"},{"head":"Трансмиссия","name":"Количество передач","value":"5"},{"head":"Трансмиссия","name":"Тип привода","value":"передний"},{"head":"Подвеска и тормоза","name":"Тип передней подвески","value":"независимая, пружинная"},{"head":"Подвеска и тормоза","name":"Передние тормоза","value":"дисковые"},{"head":"Подвеска и тормоза","name":"Задние тормоза","value":"барабанные"},{"head":"Эксплуатационные показатели","name":"Марка топлива","value":"АИ-95"},{"head":"Двигатель","name":"Тип двигателя","value":"бензин"},{"head":"Двигатель","name":"Объем двигателя, см³","value":"1598"},{"head":"Двигатель","name":"Тип наддува","value":"нет"},{"head":"Двигатель","name":"Максимальная мощность, л.с./кВт при об/мин","value":"101 / 74 "},{"head":"Двигатель","name":"Максимальный крутящий момент, Н*м при об/мин","value":"134 "},{"head":"Двигатель","name":"Расположение цилиндров","value":"рядное"},{"head":"Двигатель","name":"Количество цилиндров","value":"4"},{"head":"Двигатель","name":"Число клапанов на цилиндр","value":"4"},{"head":"Двигатель","name":"Система питания двигателя","value":"распределенный впрыск (многоточечный)"},{"head":"Двигатель","name":"Диаметр цилиндра и ход поршня, мм","value":"-"}],"url":"https://auto.ru/catalog/cars/foton/midi/20346602/20468302/specifications/20468302__20468362/"}}
{"brand":"Foton","model":"Sauvana","generation":{"name":"I","years":"2015 – н.в.","url":"https://auto.ru/catalog/cars/foton/sauvana/20809151/20809174/"},"complectation":{"name":"Модификация 2.0 MT","specification":[{"head":"Основные","name":"Объем","value":"2.0 л"},{"head":"Основные","name":"Мощность","value":"201 л.с."},{"head":"Основные","name":"Коробка","value":"механика"},{"head":"Основные","name":"Тип двигателя","value":"бензин"},{"head":"Основные","name":"Топливо","value":"АИ-95"},{"head":"Основные","name":"Привод","value":"полный"},{"head":"Общая информация","name":"Страна марки","value":"Китай"},{"head":"Общая информация","name":"Класс автомобиля","value":"J"},{"head":"Общая информация","name":"Количество дверей","value":"5"},{"head":"Общая информация","name":"Количество мест","value":"5, 7"},{"head":"Размеры, мм","name":"Длина","value":"4830"},{"head":"Размеры, мм","name":"Ширина","value":"1910"},{"head":"Размеры, мм","name":"Высота","value":"1885"},{"head":"Размеры, мм","name":"Колёсная база","value":"2790"},{"head":"Размеры, мм","name":"Клиренс","value":"220"},{"head":"Размеры, мм","name":"Ширина передней колеи","value":"1600"},{"head":"Размеры, мм","name":"Ширина задней колеи","value":"1580"},{"head":"Размеры, мм","name":"Размер колёс","value":"265/70/R16  265/65/R17"},{"head":"Объём и масса","name":"Объем багажника мин/макс, л","value":"1510/2240"},{"head":"Объём и масса","name":"Объём топливного бака, л","value":"75"},{"head":"Объём и масса","name":"Снаряженная масса, кг","value":"1940"},{"head":"Объём и масса","name":"Полная масса, кг","value":"2510"},{"head":"Трансмиссия","name":"Коробка передач","value":"механика"},{"head":"Трансмиссия","name":"Количество передач","value":"5"},{"head":"Трансмиссия","name":"Тип привода","value":"полный"},{"head":"Подвеска и тормоза","name":"Тип передней подвески","value":"независимая, пружинная"},{"head":"Подвеска и тормоза","name":"Тип задней подвески","value":"зависимая, пружинная"},{"head":"Подвеска и тормоза","name":"Передние тормоза","value":"дисковые"},{"head":"Подвеска и тормоза","name":"Задние тормоза","value":"дисковые"},{"head":"Эксплуатационные показатели","name":"Марка топлива","value":"АИ-95"},{"head":"Эксплуатационные показатели","name":"Экологический класс","value":"Euro 5"},{"head":"Двигатель","name":"Тип двигателя","value":"бензин"},{"head":"Двигатель","name":"Расположение двигателя","value":"переднее, продольное"},{"head":"Двигатель","name":"Объем двигателя, см³","value":"1981"},{"head":"Двигатель","name":"Тип наддува","value":"турбонаддув"},{"head":"Двигатель","name":"Максимальная мощность, л.с./кВт при об/мин","value":"201 / 148 при 5500"},{"head":"Двигатель","name":"Максимальный крутящий момент, Н*м при об/мин","value":"300 при 1750 – 4500"},{"head":"Двигатель","name":"Расположение цилиндров","value":"рядное"},{"head":"Двигатель","name":"Количество цилиндров","value":"4"},{"head":"Двигатель","name":"Число клапанов на цилиндр","value":"4"},{"head":"Двигатель","name":"Система питания двигателя","value":"непосредственный впрыск (прямой)"},{"head":"Двигатель","name":"Степень сжатия","value":"10"},{"head":"Двигатель","name":"Диаметр цилиндра и ход поршня, мм","value":"-"}],"url":"https://auto.ru/catalog/cars/foton/sauvana/20809151/20809174/specifications/20809174_20968009_20967866/"}}
{"brand":"Foton","model":"Sauvana","generation":{"name":"I","years":"2015 – н.в.","url":"https://auto.ru/catalog/cars/foton/sauvana/20809151/20809174/"},"complectation":{"name":"Модификация 2.0 MT","specification":[{"head":"Основные","name":"Объем","value":"2.0 л"},{"head":"Основные","name":"Мощность","value":"201 л.с."},{"head":"Основные","name":"Коробка","value":"механика"},{"head":"Основные","name":"Тип двигателя","value":"бензин"},{"head":"Основные","name":"Топливо","value":"АИ-95"},{"head":"Основные","name":"Привод","value":"полный"},{"head":"Общая информация","name":"Страна марки","value":"Китай"},{"head":"Общая информация","name":"Класс автомобиля","value":"J"},{"head":"Общая информация","name":"Количество дверей","value":"5"},{"head":"Общая информация","name":"Количество мест","value":"5, 7"},{"head":"Размеры, мм","name":"Длина","value":"4830"},{"head":"Размеры, мм","name":"Ширина","value":"1910"},{"head":"Размеры, мм","name":"Высота","value":"1885"},{"head":"Размеры, мм","name":"Колёсная база","value":"2790"},{"head":"Размеры, мм","name":"Клиренс","value":"220"},{"head":"Размеры, мм","name":"Ширина передней колеи","value":"1600"},{"head":"Размеры, мм","name":"Ширина задней колеи","value":"1580"},{"head":"Размеры, мм","name":"Размер колёс","value":"265/70/R16  265/65/R17"},{"head":"Объём и масса","name":"Объем багажника мин/макс, л","value":"1510/2240"},{"head":"Объём и масса","name":"Объём топливного бака, л","value":"75"},{"head":"Объём и масса","name":"Снаряженная масса, кг","value":"1940"},{"head":"Объём и масса","name":"Полная масса, кг","value":"2510"},{"head":"Трансмиссия","name":"Коробка передач","value":"механика"},{"head":"Трансмиссия","name":"Количество передач","value":"5"},{"head":"Трансмиссия","name":"Тип привода","value":"полный"},{"head":"Подвеска и тормоза","name":"Тип передней подвески","value":"независимая, пружинная"},{"head":"Подвеска и тормоза","name":"Тип задней подвески","value":"зависимая, пружинная"},{"head":"Подвеска и тормоза","name":"Передние тормоза","value":"дисковые"},{"head":"Подвеска и тормоза","name":"Задние тормоза","value":"дисковые"},{"head":"Эксплуатационные показатели","name":"Марка топлива","value":"АИ-95"},{"head":"Эксплуатационные показатели","name":"Экологический класс","value":"Euro 5"},{"head":"Двигатель","name":"Тип двигателя","value":"бензин"},{"head":"Двигатель","name":"Расположение двигателя","value":"переднее, продольное"},{"head":"Двигатель","name":"Объем двигателя, см³","value":"1981"},{"head":"Двигатель","name":"Тип наддува","value":"турбонаддув"},{"head":"Двигатель","name":"Максимальная мощность, л.с./кВт при об/мин","value":"201 / 148 при 5500"},{"head":"Двигатель","name":"Максимальный крутящий момент, Н*м при об/мин","value":"300 при 1750 – 4500"},{"head":"Двигатель","name":"Расположение цилиндров","value":"рядное"},{"head":"Двигатель","name":"Количество цилиндров","value":"4"},{"head":"Двигатель","name":"Число клапанов на цилиндр","value":"4"},{"head":"Двигатель","name":"Система питания двигателя","value":"непосредственный впрыск (прямой)"},{"head":"Двигатель","name":"Степень сжатия","value":"10"},{"head":"Двигатель","name":"Диаметр цилиндра и ход поршня, мм","value":"-"}],"url":"https://auto.ru/catalog/cars/foton/sauvana/20809151/20809174/specifications/20809174_21085805_20967866/"}}
{"brand":"Foton","model":"Sauvana","generation":{"name":"I","years":"2015 – н.в.","url":"https://auto.ru/catalog/cars/foton/sauvana/20809151/20809174/"},"complectation":{"name":"Модификация 2.0 MT","specification":[{"head":"Основные","name":"Объем","value":"2.0 л"},{"head":"Основные","name":"Мощность","value":"201 л.с."},{"head":"Основные","name":"Коробка","value":"механика"},{"head":"Основные","name":"Тип двигателя","value":"бензин"},{"head":"Основные","name":"Топливо","value":"АИ-95"},{"head":"Основные","name":"Привод","value":"полный"},{"head":"Общая информация","name":"Страна марки","value":"Китай"},{"head":"Общая информация","name":"Класс автомобиля","value":"J"},{"head":"Общая информация","name":"Количество дверей","value":"5"},{"head":"Общая информация","name":"Количество мест","value":"5, 7"},{"head":"Размеры, мм","name":"Длина","value":"4830"},{"head":"Размеры, мм","name":"Ширина","value":"1910"},{"head":"Размеры, мм","name":"Высота","value":"1885"},{"head":"Размеры, мм","name":"Колёсная база","value":"2790"},{"head":"Размеры, мм","name":"Клиренс","value":"220"},{"head":"Размеры, мм","name":"Ширина передней колеи","value":"1600"},{"head":"Размеры, мм","name":"Ширина задней колеи","value":"1580"},{"head":"Размеры, мм","name":"Размер колёс","value":"265/70/R16  265/65/R17"},{"head":"Объём и масса","name":"Объем багажника мин/макс, л","value":"1510/2240"},{"head":"Объём и масса","name":"Объём топливного бака, л","value":"75"},{"head":"Объём и масса","name":"Снаряженная масса, кг","value":"1940"},{"head":"Объём и масса","name":"Полная масса, кг","value":"2510"},{"head":"Трансмиссия","name":"Коробка передач","value":"механика"},{"head":"Трансмиссия","name":"Количество передач","value":"5"},{"head":"Трансмиссия","name":"Тип привода","value":"полный"},{"head":"Подвеска и тормоза","name":"Тип передней подвески","value":"независимая, пружинная"},{"head":"Подвеска и тормоза","name":"Тип задней подвески","value":"зависимая, пружинная"},{"head":"Подвеска и тормоза","name":"Передние тормоза","value":"дисковые"},{"head":"Подвеска и тормоза","name":"Задние тормоза","value":"дисковые"},{"head":"Эксплуатационные показатели","name":"Марка топлива","value":"АИ-95"},{"head":"Эксплуатационные показатели","name":"Экологический класс","value":"Euro 5"},{"head":"Двигатель","name":"Тип двигателя","value":"бензин"},{"head":"Двигатель","name":"Расположение двигателя","value":"переднее, продольное"},{"head":"Двигатель","name":"Объем двигателя, см³","value":"1981"},{"head":"Двигатель","name":"Тип наддува","value":"турбонаддув"},{"head":"Двигатель","name":"Максимальная мощность, л.с./кВт при об/мин","value":"201 / 148 при 5500"},{"head":"Двигатель","name":"Максимальный крутящий момент, Н*м при об/мин","value":"300 при 1750 – 4500"},{"head":"Двигатель","name":"Расположение цилиндров","value":"рядное"},{"head":"Двигатель","name":"Количество цилиндров","value":"4"},{"head":"Двигатель","name":"Число клапанов на цилиндр","value":"4"},{"head":"Двигатель","name":"Система питания двигателя","value":"непосредственный впрыск (прямой)"},{"head":"Двигатель","name":"Степень сжатия","value":"10"},{"head":"Двигатель","name":"Диаметр цилиндра и ход поршня, мм","value":"-"}],"url":"https://auto.ru/catalog/cars/foton/sauvana/20809151/20809174/specifications/20809174_21085801_20967866/"}}
{"brand":"Foton","model":"Sauvana","generation":{"name":"I","years":"2015 – н.в.","url":"https://auto.ru/catalog/cars/foton/sauvana/20809151/20809174/"},"complectation":{"name":"Модификация 2.0 AT","specification":[{"head":"Основные","name":"Объем","value":"2.0 л"},{"head":"Основные","name":"Мощность","value":"217 л.с."},{"head":"Основные","name":"Коробка","value":"автомат"},{"head":"Основные","name":"Тип двигателя","value":"бензин"},{"head":"Основные","name":"Топливо","value":"АИ-95"},{"head":"Основные","name":"Привод","value":"полный"},{"head":"Общая информация","name":"Страна марки","value":"Китай"},{"head":"Общая информация","name":"Класс автомобиля","value":"J"},{"head":"Общая информация","name":"Количество дверей","value":"5"},{"head":"Общая информация","name":"Количество мест","value":"5, 7"},{"head":"Размеры, мм","name":"Длина","value":"4830"},{"head":"Размеры, мм","name":"Ширина","value":"1910"},{"head":"Размеры, мм","name":"Высота","value":"1885"},{"head":"Размеры, мм","name":"Колёсная база","value":"2790"},{"head":"Размеры, мм","name":"Клиренс","value":"220"},{"head":"Размеры, мм","name":"Ширина передней колеи","value":"1600"},{"head":"Размеры, мм","name":"Ширина задней колеи","value":"1580"},{"head":"Размеры, мм","name":"Размер колёс","value":"265/70/R16  265/65/R17"},{"head":"Объём и масса","name":"Объем багажника мин/макс, л","value":"1510/2240"},{"head":"Объём и масса","name":"Объём топливного бака, л","value":"75"},{"head":"Объём и масса","name":"Снаряженная масса, кг","value":"2035"},{"head":"Объём и масса","name":"Полная масса, кг","value":"2530"},{"head":"Трансмиссия","name":"Коробка передач","value":"автомат"},{"head":"Трансмиссия","name":"Количество передач","value":"6"},{"head":"Трансмиссия","name":"Тип привода","value":"полный"},{"head":"Подвеска и тормоза","name":"Тип передней подвески","value":"независимая, пружинная"},{"head":"Подвеска и тормоза","name":"Тип задней подвески","value":"зависимая, пружинная"},{"head":"Подвеска и тормоза","name":"Передние тормоза","value":"дисковые"},{"head":"Подвеска и тормоза","name":"Задние тормоза","value":"дисковые"},{"head":"Эксплуатационные показатели","name":"Марка топлива","value":"АИ-95"},{"head":"Эксплуатационные показатели","name":"Экологический класс","value":"Euro 5"},{"head":"Двигатель","name":"Тип двигателя","value":"бензин"},{"head":"Двигатель","name":"Расположение двигателя","value":"переднее, продольное"},{"head":"Двигатель","name":"Объем двигателя, см³","value":"1981"},{"head":"Двигатель","name":"Тип наддува","value":"турбонаддув"},{"head":"Двигатель","name":"Максимальная мощность, л.с./кВт при об/мин","value":"217 / 160 при 5500"},{"head":"Двигатель","name":"Максимальный крутящий момент, Н*м при об/мин","value":"320 при 1750 – 4500"},{"head":"Двигатель","name":"Расположение цилиндров","value":"рядное"},{"head":"Двигатель","name":"Количество цилиндров","value":"4"},{"head":"Двигатель","name":"Число клапанов на цилиндр","value":"4"},{"head":"Двигатель","name":"Система питания двигателя","value":"непосредственный впрыск (прямой)"},{"head":"Двигатель","name":"Степень сжатия","value":"10"},{"head":"Двигатель","name":"Диаметр цилиндра и ход поршня, мм","value":"-"}],"url":"https://auto.ru/catalog/cars/foton/sauvana/20809151/20809174/specifications/20809174_20968018_20967879/"}}
{"brand":"Foton","model":"Sauvana","generation":{"name":"I","years":"2015 – н.в.","url":"https://auto.ru/catalog/cars/foton/sauvana/20809151/20809174/"},"complectation":{"name":"Модификация 2.0 AT","specification":[{"head":"Основные","name":"Объем","value":"2.0 л"},{"head":"Основные","name":"Мощность","value":"217 л.с."},{"head":"Основные","name":"Коробка","value":"автомат"},{"head":"Основные","name":"Тип двигателя","value":"бензин"},{"head":"Основные","name":"Топливо","value":"АИ-95"},{"head":"Основные","name":"Привод","value":"полный"},{"head":"Общая информация","name":"Страна марки","value":"Китай"},{"head":"Общая информация","name":"Класс автомобиля","value":"J"},{"head":"Общая информация","name":"Количество дверей","value":"5"},{"head":"Общая информация","name":"Количество мест","value":"5, 7"},{"head":"Размеры, мм","name":"Длина","value":"4830"},{"head":"Размеры, мм","name":"Ширина","value":"1910"},{"head":"Размеры, мм","name":"Высота","value":"1885"},{"head":"Размеры, мм","name":"Колёсная база","value":"2790"},{"head":"Размеры, мм","name":"Клиренс","value":"220"},{"head":"Размеры, мм","name":"Ширина передней колеи","value":"1600"},{"head":"Размеры, мм","name":"Ширина задней колеи","value":"1580"},{"head":"Размеры, мм","name":"Размер колёс","value":"265/70/R16  265/65/R17"},{"head":"Объём и масса","name":"Объем багажника мин/макс, л","value":"1510/2240"},{"head":"Объём и масса","name":"Объём топливного бака, л","value":"75"},{"head":"Объём и масса","name":"Снаряженная масса, кг","value":"2035"},{"head":"Объём и масса","name":"Полная масса, кг","value":"2530"},{"head":"Трансмиссия","name":"Коробка передач","value":"автомат"},{"head":"Трансмиссия","name":"Количество передач","value":"6"},{"head":"Трансмиссия","name":"Тип привода","value":"полный"},{"head":"Подвеска и тормоза","name":"Тип передней подвески","value":"независимая, пружинная"},{"head":"Подвеска и тормоза","name":"Тип задней подвески","value":"зависимая, пружинная"},{"head":"Подвеска и тормоза","name":"Передние тормоза","value":"дисковые"},{"head":"Подвеска и тормоза","name":"Задние тормоза","value":"дисковые"},{"head":"Эксплуатационные показатели","name":"Марка топлива","value":"АИ-95"},{"head":"Эксплуатационные показатели","name":"Экологический класс","value":"Euro 5"},{"head":"Двигатель","name":"Тип двигателя","value":"бензин"},{"head":"Двигатель","name":"Расположение двигателя","value":"переднее, продольное"},{"head":"Двигатель","name":"Объем двигателя, см³","value":"1981"},{"head":"Двигатель","name":"Тип наддува","value":"турбонаддув"},{"head":"Двигатель","name":"Максимальная мощность, л.с./кВт при об/мин","value":"217 / 160 при 5500"},{"head":"Двигатель","name":"Максимальный крутящий момент, Н*м при об/мин","value":"320 при 1750 – 4500"},{"head":"Двигатель","name":"Расположение цилиндров","value":"рядное"},{"head":"Двигатель","name":"Количество цилиндров","value":"4"},{"head":"Двигатель","name":"Число клапанов на цилиндр","value":"4"},{"head":"Двигатель","name":"Система питания двигателя","value":"непосредственный впрыск (прямой)"},{"head":"Двигатель","name":"Степень сжатия","value":"10"},{"head":"Двигатель","name":"Диаметр цилиндра и ход поршня, мм","value":"-"}],"url":"https://auto.ru/catalog/cars/foton/sauvana/20809151/20809174/specifications/20809174_21085813_20967879/"}}
{"brand":"Foton","model":"Sauvana","generation":{"name":"I","years":"2015 – н.в.","url":"https://auto.ru/catalog/cars/foton/sauvana/20809151/20809174/"},"complectation":{"name":"Модификация 2.0 AT","specification":[{"head":"Основные","name":"Объем","value":"2.0 л"},{"head":"Основные","name":"Мощность","value":"217 л.с."},{"head":"Основные","name":"Коробка","value":"автомат"},{"head":"Основные","name":"Тип двигателя","value":"бензин"},{"head":"Основные","name":"Топливо","value":"АИ-95"},{"head":"Основные","name":"Привод","value":"полный"},{"head":"Общая информация","name":"Страна марки","value":"Китай"},{"head":"Общая информация","name":"Класс автомобиля","value":"J"},{"head":"Общая информация","name":"Количество дверей","value":"5"},{"head":"Общая информация","name":"Количество мест","value":"5, 7"},{"head":"Размеры, мм","name":"Длина","value":"4830"},{"head":"Размеры, мм","name":"Ширина","value":"1910"},{"head":"Размеры, мм","name":"Высота","value":"1885"},{"head":"Размеры, мм","name":"Колёсная база","value":"2790"},{"head":"Размеры, мм","name":"Клиренс","value":"220"},{"head":"Размеры, мм","name":"Ширина передней колеи","value":"1600"},{"head":"Размеры, мм","name":"Ширина задней колеи","value":"1580"},{"head":"Размеры, мм","name":"Размер колёс","value":"265/70/R16  265/65/R17"},{"head":"Объём и масса","name":"Объем багажника мин/макс, л","value":"1510/2240"},{"head":"Объём и масса","name":"Объём топливного бака, л","value":"75"},{"head":"Объём и масса","name":"Снаряженная масса, кг","value":"2035"},{"head":"Объём и масса","name":"Полная масса, кг","value":"2530"},{"head":"Трансмиссия","name":"Коробка передач","value":"автомат"},{"head":"Трансмиссия","name":"Количество передач","value":"6"},{"head":"Трансмиссия","name":"Тип привода","value":"полный"},{"head":"Подвеска и тормоза","name":"Тип передней подвески","value":"независимая, пружинная"},{"head":"Подвеска и тормоза","name":"Тип задней подвески","value":"зависимая, пружинная"},{"head":"Подвеска и тормоза","name":"Передние тормоза","value":"дисковые"},{"head":"Подвеска и тормоза","name":"Задние тормоза","value":"дисковые"},{"head":"Эксплуатационные показатели","name":"Марка топлива","value":"АИ-95"},{"head":"Эксплуатационные показатели","name":"Экологический класс","value":"Euro 5"},{"head":"Двигатель","name":"Тип двигателя","value":"бензин"},{"head":"Двигатель","name":"Расположение двигателя","value":"переднее, продольное"},{"head":"Двигатель","name":"Объем двигателя, см³","value":"1981"},{"head":"Двигатель","name":"Тип наддува","value":"турбонаддув"},{"head":"Двигатель","name":"Максимальная мощность, л.с./кВт при об/мин","value":"217 / 160 при 5500"},{"head":"Двигатель","name":"Максимальный крутящий момент, Н*м при об/мин","value":"320 при 1750 – 4500"},{"head":"Двигатель","name":"Расположение цилиндров","value":"рядное"},{"head":"Двигатель","name":"Количество цилиндров","value":"4"},{"head":"Двигатель","name":"Число клапанов на цилиндр","value":"4"},{"head":"Двигатель","name":"Система питания двигателя","value":"непосредственный впрыск (прямой)"},{"head":"Двигатель","name":"Степень сжатия","value":"10"},{"head":"Двигатель","name":"Диаметр цилиндра и ход поршня, мм","value":"-"}],"url":"https://auto.ru/catalog/cars/foton/sauvana/20809151/20809174/specifications/20809174_21085809_20967879/"}}
{"brand":"Foton","model":"Sauvana","generation":{"name":"I","years":"2015 – н.в.","url":"https://auto.ru/catalog/cars/foton/sauvana/20809151/20809174/"},"complectation":{"name":"Модификация 2.4 MT","specification":[{"head":"Основные","name":"Объем","value":"2.4 л"},{"head":"Основные","name":"Мощность","value":"160 л.с."},{"head":"Основные","name":"Коробка","value":"механика"},{"head":"Основные","name":"Тип двигателя","value":"бензин"},{"head":"Основные","name":"Топливо","value":"АИ-95"},{"head":"Основные","name":"Привод","value":"задний"},{"head":"Общая информация","name":"Страна марки","value":"Китай"},{"head":"Общая информация","name":"Класс автомобиля","value":"J"},{"head":"Общая информация","name":"Количество дверей","value":"5"},{"head":"Общая информация","name":"Количество мест","value":"5, 7"},{"head":"Размеры, мм","name":"Длина","value":"4830"},{"head":"Размеры, мм","name":"Ширина","value":"1910"},{"head":"Размеры, мм","name":"Высота","value":"1885"},{"head":"Размеры, мм","name":"Колёсная база","value":"2790"},{"head":"Размеры, мм","name":"Клиренс","value":"220"},{"head":"Размеры, мм","name":"Ширина передней колеи","value":"1600"},{"head":"Размеры, мм","name":"Ширина задней колеи","value":"1580"},{"head":"Размеры, мм","name":"Размер колёс","value":"265/65/R17"},{"head":"Объём и масса","name":"Объем багажника мин/макс, л","value":"1510/2240"},{"head":"Объём и масса","name":"Объём топливного бака, л","value":"75"},{"head":"Объём и масса","name":"Снаряженная масса, кг","value":"1940"},{"head":"Трансмиссия","name":"Коробка передач","value":"механика"},{"head":"Трансмиссия","name":"Количество передач","value":"5"},{"head":"Трансмиссия","name":"Тип привода","value":"задний"},{"head":"Подвеска и тормоза","name":"Тип передней подвески","value":"независимая, пружинная"},{"head":"Подвеска и тормоза","name":"Тип задней подвески","value":"зависимая, пружинная"},{"head":"Подвеска и тормоза","name":"Передние тормоза","value":"дисковые"},{"head":"Подвеска и тормоза","name":"Задние тормоза","value":"дисковые"},{"head":"Эксплуатационные показатели","name":"Максимальная скорость, км/ч","value":"150"},{"head":"Эксплуатационные показатели","name":"Марка топлива","value":"АИ-95"},{"head":"Двигатель","name":"Тип двигателя","value":"бензин"},{"head":"Двигатель","name":"Расположение двигателя","value":"переднее, продольное"},{"head":"Двигатель","name":"Объем двигателя, см³","value":"2378"},{"head":"Двигатель","name":"Тип наддува","value":"нет"},{"head":"Двигатель","name":"Максимальная мощность, л.с./кВт при об/мин","value":"160 / 118 при 5750"},{"head":"Двигатель","name":"Максимальный крутящий момент, Н*м при об/мин","value":"213 при 4000"},{"head":"Двигатель","name":"Расположение цилиндров","value":"рядное"},{"head":"Двигатель","name":"Количество цилиндров","value":"4"},{"head":"Двигатель","name":"Число клапанов на цилиндр","value":"4"},{"head":"Двигатель","name":"Система питания двигателя","value":"распределенный впрыск (многоточечный)"},{"head":"Двигатель","name":"Степень сжатия","value":"9.5"},{"head":"Двигатель","name":"Диаметр цилиндра и ход поршня, мм","value":"87 × 100"}],"url":"https://auto.ru/catalog/cars/foton/sauvana/20809151/20809174/specifications/20809174__20809234/"}}
{"brand":"Foton","model":"Sauvana","generation":{"name":"I","years":"2015 – н.в.","url":"https://auto.ru/catalog/cars/foton/sauvana/20809151/20809174/"},"complectation":{"name":"Модификация 2.4 MT","specification":[{"head":"Основные","name":"Объем","value":"2.4 л"},{"head":"Основные","name":"Мощность","value":"160 л.с."},{"head":"Основные","name":"Коробка","value":"механика"},{"head":"Основные","name":"Тип двигателя","value":"бензин"},{"head":"Основные","name":"Топливо","value":"АИ-95"},{"head":"Основные","name":"Привод","value":"полный"},{"head":"Общая информация","name":"Страна марки","value":"Китай"},{"head":"Общая информация","name":"Класс автомобиля","value":"J"},{"head":"Общая информация","name":"Количество дверей","value":"5"},{"head":"Общая информация","name":"Количество мест","value":"5, 7"},{"head":"Размеры, мм","name":"Длина","value":"4830"},{"head":"Размеры, мм","name":"Ширина","value":"1910"},{"head":"Размеры, мм","name":"Высота","value":"1885"},{"head":"Размеры, мм","name":"Колёсная база","value":"2790"},{"head":"Размеры, мм","name":"Клиренс","value":"220"},{"head":"Размеры, мм","name":"Ширина передней колеи","value":"1600"},{"head":"Размеры, мм","name":"Ширина задней колеи","value":"1580"},{"head":"Размеры, мм","name":"Размер колёс","value":"265/65/R17"},{"head":"Объём и масса","name":"Объем багажника мин/макс, л","value":"1510/2240"},{"head":"Объём и масса","name":"Объём топливного бака, л","value":"75"},{"head":"Объём и масса","name":"Снаряженная масса, кг","value":"1940"},{"head":"Трансмиссия","name":"Коробка передач","value":"механика"},{"head":"Трансмиссия","name":"Количество передач","value":"5"},{"head":"Трансмиссия","name":"Тип привода","value":"полный"},{"head":"Подвеска и тормоза","name":"Тип передней подвески","value":"независимая, пружинная"},{"head":"Подвеска и тормоза","name":"Тип задней подвески","value":"зависимая, пружинная"},{"head":"Подвеска и тормоза","name":"Передние тормоза","value":"дисковые"},{"head":"Подвеска и тормоза","name":"Задние тормоза","value":"дисковые"},{"head":"Эксплуатационные показатели","name":"Марка топлива","value":"АИ-95"},{"head":"Двигатель","name":"Тип двигателя","value":"бензин"},{"head":"Двигатель","name":"Расположение двигателя","value":"переднее, продольное"},{"head":"Двигатель","name":"Объем двигателя, см³","value":"2378"},{"head":"Двигатель","name":"Тип наддува","value":"нет"},{"head":"Двигатель","name":"Максимальная мощность, л.с./кВт при об/мин","value":"160 / 118 при 5750"},{"head":"Двигатель","name":"Максимальный крутящий момент, Н*м при об/мин","value":"213 при 4000"},{"head":"Двигатель","name":"Расположение цилиндров","value":"рядное"},{"head":"Двигатель","name":"Количество цилиндров","value":"4"},{"head":"Двигатель","name":"Число клапанов на цилиндр","value":"4"},{"head":"Двигатель","name":"Система питания двигателя","value":"распределенный впрыск (многоточечный)"},{"head":"Двигатель","name":"Степень сжатия","value":"9.5"},{"head":"Двигатель","name":"Диаметр цилиндра и ход поршня, мм","value":"87 × 100"}],"url":"https://auto.ru/catalog/cars/foton/sauvana/20809151/20809174/specifications/20809174__20912063/"}}
{"brand":"Foton","model":"Sauvana","generation":{"name":"I","years":"2015 – н.в.","url":"https://auto.ru/catalog/cars/foton/sauvana/20809151/20809174/"},"complectation":{"name":"Модификация 2.8 MT","specification":[{"head":"Основные","name":"Объем","value":"2.8 л"},{"head":"Основные","name":"Мощность","value":"177 л.с."},{"head":"Основные","name":"Коробка","value":"механика"},{"head":"Основные","name":"Тип двигателя","value":"дизель"},{"head":"Основные","name":"Топливо","value":"ДТ"},{"head":"Основные","name":"Привод","value":"задний"},{"head":"Основные","name":"Разгон","value":"13.9 с"},{"head":"Общая информация","name":"Страна марки","value":"Китай"},{"head":"Общая информация","name":"Класс автомобиля","value":"J"},{"head":"Общая информация","name":"Количество дверей","value":"5"},{"head":"Общая информация","name":"Количество мест","value":"5, 7"},{"head":"Размеры, мм","name":"Длина","value":"4830"},{"head":"Размеры, мм","name":"Ширина","value":"1910"},{"head":"Размеры, мм","name":"Высота","value":"1885"},{"head":"Размеры, мм","name":"Колёсная база","value":"2790"},{"head":"Размеры, мм","name":"Клиренс","value":"220"},{"head":"Размеры, мм","name":"Ширина передней колеи","value":"1600"},{"head":"Размеры, мм","name":"Ширина задней колеи","value":"1580"},{"head":"Размеры, мм","name":"Размер колёс","value":"265/65/R17"},{"head":"Объём и масса","name":"Объем багажника мин/макс, л","value":"1510/2240"},{"head":"Объём и масса","name":"Объём топливного бака, л","value":"75"},{"head":"Объём и масса","name":"Снаряженная масса, кг","value":"1940"},{"head":"Трансмиссия","name":"Коробка передач","value":"механика"},{"head":"Трансмиссия","name":"Количество передач","value":"5"},{"head":"Трансмиссия","name":"Тип привода","value":"задний"},{"head":"Подвеска и тормоза","name":"Тип передней подвески","value":"независимая, пружинная"},{"head":"Подвеска и тормоза","name":"Тип задней подвески","value":"зависимая, пружинная"},{"head":"Подвеска и тормоза","name":"Передние тормоза","value":"дисковые"},{"head":"Подвеска и тормоза","name":"Задние тормоза","value":"дисковые"},{"head":"Эксплуатационные показатели","name":"Максимальная скорость, км/ч","value":"150"},{"head":"Эксплуатационные показатели","name":"Разгон до 100 км/ч, с","value":"13.9"},{"head":"Эксплуатационные показатели","name":"Марка топлива","value":"ДТ"},{"head":"Двигатель","name":"Тип двигателя","value":"дизель"},{"head":"Двигатель","name":"Расположение двигателя","value":"переднее, продольное"},{"head":"Двигатель","name":"Объем двигателя, см³","value":"2780"},{"head":"Двигатель","name":"Тип наддува","value":"турбонаддув"},{"head":"Двигатель","name":"Максимальная мощность, л.с./кВт при об/мин","value":"177 / 130 "},{"head":"Двигатель","name":"Максимальный крутящий момент, Н*м при об/мин","value":"360 "},{"head":"Двигатель","name":"Расположение цилиндров","value":"рядное"},{"head":"Двигатель","name":"Количество цилиндров","value":"4"},{"head":"Двигатель","name":"Число клапанов на цилиндр","value":"4"},{"head":"Двигатель","name":"Диаметр цилиндра и ход поршня, мм","value":"-"}],"url":"https://auto.ru/catalog/cars/foton/sauvana/20809151/20809174/specifications/20809174__20809210/"}}
{"brand":"Foton","model":"Sauvana","generation":{"name":"I","years":"2015 – н.в.","url":"https://auto.ru/catalog/cars/foton/sauvana/20809151/20809174/"},"complectation":{"name":"Модификация 2.8 MT","specification":[{"head":"Основные","name":"Объем","value":"2.8 л"},{"head":"Основные","name":"Мощность","value":"177 л.с."},{"head":"Основные","name":"Коробка","value":"механика"},{"head":"Основные","name":"Тип двигателя","value":"дизель"},{"head":"Основные","name":"Топливо","value":"ДТ"},{"head":"Основные","name":"Привод","value":"полный"},{"head":"Общая информация","name":"Страна марки","value":"Китай"},{"head":"Общая информация","name":"Класс автомобиля","value":"J"},{"head":"Общая информация","name":"Количество дверей","value":"5"},{"head":"Общая информация","name":"Количество мест","value":"5, 7"},{"head":"Размеры, мм","name":"Длина","value":"4830"},{"head":"Размеры, мм","name":"Ширина","value":"1910"},{"head":"Размеры, мм","name":"Высота","value":"1885"},{"head":"Размеры, мм","name":"Колёсная база","value":"2790"},{"head":"Размеры, мм","name":"Клиренс","value":"220"},{"head":"Размеры, мм","name":"Ширина передней колеи","value":"1600"},{"head":"Размеры, мм","name":"Ширина задней колеи","value":"1580"},{"head":"Размеры, мм","name":"Размер колёс","value":"265/65/R17"},{"head":"Объём и масса","name":"Объем багажника мин/макс, л","value":"1510/2240"},{"head":"Объём и масса","name":"Объём топливного бака, л","value":"75"},{"head":"Объём и масса","name":"Снаряженная масса, кг","value":"1940"},{"head":"Трансмиссия","name":"Коробка передач","value":"механика"},{"head":"Трансмиссия","name":"Количество передач","value":"5"},{"head":"Трансмиссия","name":"Тип привода","value":"полный"},{"head":"Подвеска и тормоза","name":"Тип передней подвески","value":"независимая, пружинная"},{"head":"Подвеска и тормоза","name":"Тип задней подвески","value":"зависимая, пружинная"},{"head":"Подвеска и тормоза","name":"Передние тормоза","value":"дисковые"},{"head":"Подвеска и тормоза","name":"Задние тормоза","value":"дисковые"},{"head":"Эксплуатационные показатели","name":"Марка топлива","value":"ДТ"},{"head":"Двигатель","name":"Тип двигателя","value":"дизель"},{"head":"Двигатель","name":"Расположение двигателя","value":"переднее, продольное"},{"head":"Двигатель","name":"Объем двигателя, см³","value":"2780"},{"head":"Двигатель","name":"Тип наддува","value":"турбонаддув"},{"head":"Двигатель","name":"Максимальная мощность, л.с./кВт при об/мин","value":"177 / 130 "},{"head":"Двигатель","name":"Максимальный крутящий момент, Н*м при об/мин","value":"360 "},{"head":"Двигатель","name":"Расположение цилиндров","value":"рядное"},{"head":"Двигатель","name":"Количество цилиндров","value":"4"},{"head":"Двигатель","name":"Число клапанов на цилиндр","value":"4"},{"head":"Двигатель","name":"Диаметр цилиндра и ход поршня, мм","value":"-"}],"url":"https://auto.ru/catalog/cars/foton/sauvana/20809151/20809174/specifications/20809174__20912069/"}}
{"brand":"Foton","model":"Tunland","generation":{"name":"","years":"2011 – 2018","url":"https://auto.ru/catalog/cars/foton/tunland/20346611/20468321/"},"complectation":{"name":"Модификация 2.8 MT","specification":[{"head":"Основные","name":"Объем","value":"2.8 л"},{"head":"Основные","name":"Мощность","value":"163 л.с."},{"head":"Основные","name":"Коробка","value":"механика"},{"head":"Основные","name":"Тип двигателя","value":"дизель"},{"head":"Основные","name":"Топливо","value":"ДТ"},{"head":"Основные","name":"Привод","value":"полный"},{"head":"Общая информация","name":"Страна марки","value":"Китай"},{"head":"Общая информация","name":"Класс автомобиля","value":"J"},{"head":"Общая информация","name":"Количество дверей","value":"4"},{"head":"Общая информация","name":"Количество мест","value":"5"},{"head":"Размеры, мм","name":"Длина","value":"5310"},{"head":"Размеры, мм","name":"Ширина","value":"1880"},{"head":"Размеры, мм","name":"Высота","value":"1860"},{"head":"Размеры, мм","name":"Колёсная база","value":"3105"},{"head":"Размеры, мм","name":"Клиренс","value":"200"},{"head":"Размеры, мм","name":"Ширина передней колеи","value":"1580"},{"head":"Размеры, мм","name":"Ширина задней колеи","value":"1580"},{"head":"Размеры, мм","name":"Размер колёс","value":"245/70/R16"},{"head":"Объём и масса","name":"Объем багажника мин/макс, л","value":"-"},{"head":"Объём и масса","name":"Снаряженная масса, кг","value":"1950"},{"head":"Объём и масса","name":"Полная масса, кг","value":"2975"},{"head":"Трансмиссия","name":"Коробка передач","value":"механика"},{"head":"Трансмиссия","name":"Количество передач","value":"5"},{"head":"Трансмиссия","name":"Тип привода","value":"полный"},{"head":"Подвеска и тормоза","name":"Тип передней подвески","value":"независимая, пружинная"},{"head":"Подвеска и тормоза","name":"Тип задней подвески","value":"зависимая, рессорная"},{"head":"Подвеска и тормоза","name":"Передние тормоза","value":"дисковые вентилируемые"},{"head":"Подвеска и тормоза","name":"Задние тормоза","value":"барабанные"},{"head":"Эксплуатационные показатели","name":"Максимальная скорость, км/ч","value":"160"},{"head":"Эксплуатационные показатели","name":"Марка топлива","value":"ДТ"},{"head":"Эксплуатационные показатели","name":"Экологический класс","value":"Euro 4"},{"head":"Двигатель","name":"Тип двигателя","value":"дизель"},{"head":"Двигатель","name":"Расположение двигателя","value":"переднее, продольное"},{"head":"Двигатель","name":"Объем двигателя, см³","value":"2776"},{"head":"Двигатель","name":"Тип наддува","value":"турбонаддув"},{"head":"Двигатель","name":"Максимальная мощность, л.с./кВт при об/мин","value":"163 / 120 при 3600"},{"head":"Двигатель","name":"Максимальный крутящий момент, Н*м при об/мин","value":"360 при 1800 – 3000"},{"head":"Двигатель","name":"Расположение цилиндров","value":"рядное"},{"head":"Двигатель","name":"Количество цилиндров","value":"4"},{"head":"Двигатель","name":"Число клапанов на цилиндр","value":"4"},{"head":"Двигатель","name":"Диаметр цилиндра и ход поршня, мм","value":"-"}],"url":"https://auto.ru/catalog/cars/foton/tunland/20346611/20468321/specifications/20468321_20775235_20468352/"}}
{"brand":"Foton","model":"Tunland","generation":{"name":"","years":"2011 – 2018","url":"https://auto.ru/catalog/cars/foton/tunland/20346611/20468321/"},"complectation":{"name":"Модификация 2.8 MT","specification":[{"head":"Основные","name":"Объем","value":"2.8 л"},{"head":"Основные","name":"Мощность","value":"163 л.с."},{"head":"Основные","name":"Коробка","value":"механика"},{"head":"Основные","name":"Тип двигателя","value":"дизель"},{"head":"Основные","name":"Топливо","value":"ДТ"},{"head":"Основные","name":"Привод","value":"полный"},{"head":"Общая информация","name":"Страна марки","value":"Китай"},{"head":"Общая информация","name":"Класс автомобиля","value":"J"},{"head":"Общая информация","name":"Количество дверей","value":"4"},{"head":"Общая информация","name":"Количество мест","value":"5"},{"head":"Размеры, мм","name":"Длина","value":"5310"},{"head":"Размеры, мм","name":"Ширина","value":"1880"},{"head":"Размеры, мм","name":"Высота","value":"1860"},{"head":"Размеры, мм","name":"Колёсная база","value":"3105"},{"head":"Размеры, мм","name":"Клиренс","value":"200"},{"head":"Размеры, мм","name":"Ширина передней колеи","value":"1580"},{"head":"Размеры, мм","name":"Ширина задней колеи","value":"1580"},{"head":"Размеры, мм","name":"Размер колёс","value":"245/70/R16"},{"head":"Объём и масса","name":"Объем багажника мин/макс, л","value":"-"},{"head":"Объём и масса","name":"Снаряженная масса, кг","value":"1950"},{"head":"Объём и масса","name":"Полная масса, кг","value":"2975"},{"head":"Трансмиссия","name":"Коробка передач","value":"механика"},{"head":"Трансмиссия","name":"Количество передач","value":"5"},{"head":"Трансмиссия","name":"Тип привода","value":"полный"},{"head":"Подвеска и тормоза","name":"Тип передней подвески","value":"независимая, пружинная"},{"head":"Подвеска и тормоза","name":"Тип задней подвески","value":"зависимая, рессорная"},{"head":"Подвеска и тормоза","name":"Передние тормоза","value":"дисковые вентилируемые"},{"head":"Подвеска и тормоза","name":"Задние тормоза","value":"барабанные"},{"head":"Эксплуатационные показатели","name":"Максимальная скорость, км/ч","value":"160"},{"head":"Эксплуатационные показатели","name":"Марка топлива","value":"ДТ"},{"head":"Эксплуатационные показатели","name":"Экологический класс","value":"Euro 4"},{"head":"Двигатель","name":"Тип двигателя","value":"дизель"},{"head":"Двигатель","name":"Расположение двигателя","value":"переднее, продольное"},{"head":"Двигатель","name":"Объем двигателя, см³","value":"2776"},{"head":"Двигатель","name":"Тип наддува","value":"турбонаддув"},{"head":"Двигатель","name":"Максимальная мощность, л.с./кВт при об/мин","value":"163 / 120 при 3600"},{"head":"Двигатель","name":"Максимальный крутящий момент, Н*м при об/мин","value":"360 при 1800 – 3000"},{"head":"Двигатель","name":"Расположение цилиндров","value":"рядное"},{"head":"Двигатель","name":"Количество цилиндров","value":"4"},{"head":"Двигатель","name":"Число клапанов на цилиндр","value":"4"},{"head":"Двигатель","name":"Диаметр цилиндра и ход поршня, мм","value":"-"}],"url":"https://auto.ru/catalog/cars/foton/tunland/20346611/20468321/specifications/20468321_20775243_20468352/"}}
