{"brand":"Bristol","model":"Blenheim","generation":{"name":"Series 3","years":"2000 – 2011","url":"https://auto.ru/catalog/cars/bristol/blenheim/20344717/20465924/"},"complectation":{"name":"Модификация 5.9 AT","specification":[{"head":"Основные","name":"Объем","value":"5.9 л"},{"head":"Основные","name":"Мощность","value":"354 л.с."},{"head":"Основные","name":"Коробка","value":"автомат"},{"head":"Основные","name":"Тип двигателя","value":"бензин"},{"head":"Основные","name":"Топливо","value":"АИ-95"},{"head":"Основные","name":"Привод","value":"задний"},{"head":"Основные","name":"Разгон","value":"6.6 с"},{"head":"Общая информация","name":"Страна марки","value":"Великобритания"},{"head":"Общая информация","name":"Класс автомобиля","value":"S"},{"head":"Общая информация","name":"Количество дверей","value":"2"},{"head":"Общая информация","name":"Количество мест","value":"4"},{"head":"Размеры, мм","name":"Длина","value":"4825"},{"head":"Размеры, мм","name":"Ширина","value":"1765"},{"head":"Размеры, мм","name":"Высота","value":"1440"},{"head":"Размеры, мм","name":"Колёсная база","value":"2900"},{"head":"Размеры, мм","name":"Клиренс","value":"130"},{"head":"Размеры, мм","name":"Ширина передней колеи","value":"1450"},{"head":"Размеры, мм","name":"Ширина задней колеи","value":"1460"},{"head":"Размеры, мм","name":"Размер колёс","value":"215/70/R15"},{"head":"Объём и масса","name":"Объем багажника мин/макс, л","value":"540"},{"head":"Объём и масса","name":"Объём топливного бака, л","value":"82"},{"head":"Объём и масса","name":"Снаряженная масса, кг","value":"1740"},{"head":"Трансмиссия","name":"Коробка передач","value":"автомат"},{"head":"Трансмиссия","name":"Количество передач","value":"4"},{"head":"Трансмиссия","name":"Тип привода","value":"задний"},{"head":"Подвеска и тормоза","name":"Тип передней подвески","value":"независимая, пружинная"},{"head":"Подвеска и тормоза","name":"Тип задней подвески","value":"полунезависимая, торсионная"},{"head":"Подвеска и тормоза","name":"Передние тормоза","value":"дисковые"},{"head":"Подвеска и тормоза","name":"Задние тормоза","value":"дисковые"},{"head":"Эксплуатационные показатели","name":"Максимальная скорость, км/ч","value":"250"},{"head":"Эксплуатационные показатели","name":"Разгон до 100 км/ч, с","value":"6.6"},{"head":"Эксплуатационные показатели","name":"Расход топлива, л город/трасса","value":"18/10"},{"head":"Эксплуатационные показатели","name":"Марка топлива","value":"АИ-95"},{"head":"Двигатель","name":"Тип двигателя","value":"бензин"},{"head":"Двигатель","name":"Объем двигателя, см³","value":"5898"},{"head":"Двигатель","name":"Тип наддува","value":"нет"},{"head":"Двигатель","name":"Максимальная мощность, л.с./кВт при об/мин","value":"354 / 260 при 5500"},{"head":"Двигатель","name":"Максимальный крутящий момент, Н*м при об/мин","value":"500 при 4000"},{"head":"Двигатель","name":"Расположение цилиндров","value":"V-образное"},{"head":"Двигатель","name":"Количество цилиндров","value":"8"},{"head":"Двигатель","name":"Система питания двигателя","value":"распределенный впрыск (многоточечный)"},{"head":"Двигатель","name":"Степень сжатия","value":"9.8"},{"head":"Двигатель","name":"Диаметр цилиндра и ход поршня, мм","value":"101.6 × 90.93"}],"url":"https://auto.ru/catalog/cars/bristol/blenheim/20344717/20465924/specifications/20465924__20465966/"}}
{"brand":"Bristol","model":"Blenheim","generation":{"name":"Series 3","years":"2000 – 2011","url":"https://auto.ru/catalog/cars/bristol/blenheim/20344717/20465924/"},"complectation":{"name":"Модификация 5.9 AT","specification":[{"head":"Основные","name":"Объем","value":"5.9 л"},{"head":"Основные","name":"Мощность","value":"390 л.с."},{"head":"Основные","name":"Коробка","value":"автомат"},{"head":"Основные","name":"Тип двигателя","value":"бензин"},{"head":"Основные","name":"Топливо","value":"АИ-95"},{"head":"Основные","name":"Привод","value":"задний"},{"head":"Основные","name":"Разгон","value":"5.4 с"},{"head":"Общая информация","name":"Страна марки","value":"Великобритания"},{"head":"Общая информация","name":"Класс автомобиля","value":"S"},{"head":"Общая информация","name":"Количество дверей","value":"2"},{"head":"Общая информация","name":"Количество мест","value":"4"},{"head":"Размеры, мм","name":"Длина","value":"4825"},{"head":"Размеры, мм","name":"Ширина","value":"1765"},{"head":"Размеры, мм","name":"Высота","value":"1440"},{"head":"Размеры, мм","name":"Колёсная база","value":"2900"},{"head":"Размеры, мм","name":"Клиренс","value":"130"},{"head":"Размеры, мм","name":"Ширина передней колеи","value":"1450"},{"head":"Размеры, мм","name":"Ширина задней колеи","value":"1460"},{"head":"Размеры, мм","name":"Размер колёс","value":"225/60/R16"},{"head":"Объём и масса","name":"Объем багажника мин/макс, л","value":"540"},{"head":"Объём и масса","name":"Объём топливного бака, л","value":"82"},{"head":"Объём и масса","name":"Снаряженная масса, кг","value":"1755"},{"head":"Трансмиссия","name":"Коробка передач","value":"автомат"},{"head":"Трансмиссия","name":"Количество передач","value":"4"},{"head":"Трансмиссия","name":"Тип привода","value":"задний"},{"head":"Подвеска и тормоза","name":"Тип передней подвески","value":"независимая, пружинная"},{"head":"Подвеска и тормоза","name":"Тип задней подвески","value":"полунезависимая, торсионная"},{"head":"Подвеска и тормоза","name":"Передние тормоза","value":"дисковые"},{"head":"Подвеска и тормоза","name":"Задние тормоза","value":"дисковые"},{"head":"Эксплуатационные показатели","name":"Максимальная скорость, км/ч","value":"250"},{"head":"Эксплуатационные показатели","name":"Разгон до 100 км/ч, с","value":"5.4"},{"head":"Эксплуатационные показатели","name":"Расход топлива, л город/трасса","value":"18/10"},{"head":"Эксплуатационные показатели","name":"Марка топлива","value":"АИ-95"},{"head":"Двигатель","name":"Тип двигателя","value":"бензин"},{"head":"Двигатель","name":"Объем двигателя, см³","value":"5900"},{"head":"Двигатель","name":"Тип наддува","value":"нет"},{"head":"Двигатель","name":"Максимальная мощность, л.с./кВт при об/мин","value":"390 / 287 при 5500"},{"head":"Двигатель","name":"Максимальный крутящий момент, Н*м при об/мин","value":"500 при 4000"},{"head":"Двигатель","name":"Расположение цилиндров","value":"V-образное"},{"head":"Двигатель","name":"Количество цилиндров","value":"8"},{"head":"Двигатель","name":"Число клапанов на цилиндр","value":"4"},{"head":"Двигатель","name":"Система питания двигателя","value":"распределенный впрыск (многоточечный)"},{"head":"Двигатель","name":"Степень сжатия","value":"9.25"},{"head":"Двигатель","name":"Диаметр цилиндра и ход поршня, мм","value":"101.6 × 90.93"}],"url":"https://auto.ru/catalog/cars/bristol/blenheim/20344717/20465924/specifications/20465924__20465978/"}}
{"brand":"Bristol","model":"Blenheim","generation":{"name":"Series 2","years":"1997 – 2000","url":"https://auto.ru/catalog/cars/bristol/blenheim/20344696/20465783/"},"complectation":{"name":"Модификация 5.9 AT","specification":[{"head":"Основные","name":"Объем","value":"5.9 л"},{"head":"Основные","name":"Мощность","value":"265 л.с."},{"head":"Основные","name":"Коробка","value":"автомат"},{"head":"Основные","name":"Тип двигателя","value":"бензин"},{"head":"Основные","name":"Топливо","value":"АИ-95"},{"head":"Основные","name":"Привод","value":"задний"},{"head":"Основные","name":"Разгон","value":"6.6 с"},{"head":"Общая информация","name":"Страна марки","value":"Великобритания"},{"head":"Общая информация","name":"Класс автомобиля","value":"S"},{"head":"Общая информация","name":"Количество дверей","value":"2"},{"head":"Общая информация","name":"Количество мест","value":"4"},{"head":"Размеры, мм","name":"Длина","value":"4825"},{"head":"Размеры, мм","name":"Ширина","value":"1765"},{"head":"Размеры, мм","name":"Высота","value":"1440"},{"head":"Размеры, мм","name":"Колёсная база","value":"2900"},{"head":"Размеры, мм","name":"Клиренс","value":"130"},{"head":"Размеры, мм","name":"Ширина передней колеи","value":"1430"},{"head":"Размеры, мм","name":"Ширина задней колеи","value":"1440"},{"head":"Размеры, мм","name":"Размер колёс","value":"215/70/R15"},{"head":"Объём и масса","name":"Объем багажника мин/макс, л","value":"540"},{"head":"Объём и масса","name":"Объём топливного бака, л","value":"82"},{"head":"Объём и масса","name":"Снаряженная масса, кг","value":"1740"},{"head":"Трансмиссия","name":"Коробка передач","value":"автомат"},{"head":"Трансмиссия","name":"Количество передач","value":"4"},{"head":"Трансмиссия","name":"Тип привода","value":"задний"},{"head":"Подвеска и тормоза","name":"Тип передней подвески","value":"независимая, пружинная"},{"head":"Подвеска и тормоза","name":"Тип задней подвески","value":"полунезависимая, торсионная"},{"head":"Подвеска и тормоза","name":"Передние тормоза","value":"дисковые"},{"head":"Подвеска и тормоза","name":"Задние тормоза","value":"дисковые"},{"head":"Эксплуатационные показатели","name":"Максимальная скорость, км/ч","value":"252"},{"head":"Эксплуатационные показатели","name":"Разгон до 100 км/ч, с","value":"6.6"},{"head":"Эксплуатационные показатели","name":"Расход топлива, л город/трасса","value":"18/10"},{"head":"Эксплуатационные показатели","name":"Марка топлива","value":"АИ-95"},{"head":"Двигатель","name":"Тип двигателя","value":"бензин"},{"head":"Двигатель","name":"Объем двигателя, см³","value":"5898"},{"head":"Двигатель","name":"Тип наддува","value":"нет"},{"head":"Двигатель","name":"Максимальная мощность, л.с./кВт при об/мин","value":"265 / 195 при 4000"},{"head":"Двигатель","name":"Максимальный крутящий момент, Н*м при об/мин","value":"460 при 3200"},{"head":"Двигатель","name":"Расположение цилиндров","value":"V-образное"},{"head":"Двигатель","name":"Количество цилиндров","value":"8"},{"head":"Двигатель","name":"Система питания двигателя","value":"распределенный впрыск (многоточечный)"},{"head":"Двигатель","name":"Степень сжатия","value":"8.9"},{"head":"Двигатель","name":"Диаметр цилиндра и ход поршня, мм","value":"101.6 × 90.93"}],"url":"https://auto.ru/catalog/cars/bristol/blenheim/20344696/20465783/specifications/20465783__20465815/"}}
{"brand":"Bristol","model":"Blenheim","generation":{"name":"Series 1","years":"1993 – 1997","url":"https://auto.ru/catalog/cars/bristol/blenheim/20344675/20465778/"},"complectation":{"name":"Модификация 5.9 AT","specification":[{"head":"Основные","name":"Объем","value":"5.9 л"},{"head":"Основные","name":"Мощность","value":"265 л.с."},{"head":"Основные","name":"Коробка","value":"автомат"},{"head":"Основные","name":"Тип двигателя","value":"бензин"},{"head":"Основные","name":"Топливо","value":"АИ-95"},{"head":"Основные","name":"Привод","value":"задний"},{"head":"Основные","name":"Разгон","value":"6.6 с"},{"head":"Общая информация","name":"Страна марки","value":"Великобритания"},{"head":"Общая информация","name":"Класс автомобиля","value":"S"},{"head":"Общая информация","name":"Количество дверей","value":"2"},{"head":"Общая информация","name":"Количество мест","value":"4"},{"head":"Размеры, мм","name":"Длина","value":"4825"},{"head":"Размеры, мм","name":"Ширина","value":"1765"},{"head":"Размеры, мм","name":"Высота","value":"1440"},{"head":"Размеры, мм","name":"Колёсная база","value":"2900"},{"head":"Размеры, мм","name":"Клиренс","value":"130"},{"head":"Размеры, мм","name":"Ширина передней колеи","value":"1430"},{"head":"Размеры, мм","name":"Ширина задней колеи","value":"1440"},{"head":"Размеры, мм","name":"Размер колёс","value":"215/70/R15"},{"head":"Объём и масса","name":"Объем багажника мин/макс, л","value":"540"},{"head":"Объём и масса","name":"Объём топливного бака, л","value":"82"},{"head":"Объём и масса","name":"Снаряженная масса, кг","value":"1740"},{"head":"Трансмиссия","name":"Коробка передач","value":"автомат"},{"head":"Трансмиссия","name":"Количество передач","value":"4"},{"head":"Трансмиссия","name":"Тип привода","value":"задний"},{"head":"Подвеска и тормоза","name":"Тип передней подвески","value":"независимая, пружинная"},{"head":"Подвеска и тормоза","name":"Тип задней подвески","value":"полунезависимая, торсионная"},{"head":"Подвеска и тормоза","name":"Передние тормоза","value":"дисковые"},{"head":"Подвеска и тормоза","name":"Задние тормоза","value":"дисковые"},{"head":"Эксплуатационные показатели","name":"Максимальная скорость, км/ч","value":"252"},{"head":"Эксплуатационные показатели","name":"Разгон до 100 км/ч, с","value":"6.6"},{"head":"Эксплуатационные показатели","name":"Расход топлива, л город/трасса","value":"18/10"},{"head":"Эксплуатационные показатели","name":"Марка топлива","value":"АИ-95"},{"head":"Двигатель","name":"Тип двигателя","value":"бензин"},{"head":"Двигатель","name":"Объем двигателя, см³","value":"5898"},{"head":"Двигатель","name":"Тип наддува","value":"нет"},{"head":"Двигатель","name":"Максимальная мощность, л.с./кВт при об/мин","value":"265 / 195 при 4000"},{"head":"Двигатель","name":"Максимальный крутящий момент, Н*м при об/мин","value":"460 при 3200"},{"head":"Двигатель","name":"Расположение цилиндров","value":"V-образное"},{"head":"Двигатель","name":"Количество цилиндров","value":"8"},{"head":"Двигатель","name":"Система питания двигателя","value":"распределенный впрыск (многоточечный)"},{"head":"Двигатель","name":"Степень сжатия","value":"8.9"},{"head":"Двигатель","name":"Диаметр цилиндра и ход поршня, мм","value":"101.6 × 90.93"}],"url":"https://auto.ru/catalog/cars/bristol/blenheim/20344675/20465778/specifications/20465778__20465810/"}}
{"brand":"Bristol","model":"Blenheim Speedster","generation":{"name":"","years":"2003 – 2011","url":"https://auto.ru/catalog/cars/bristol/blenheim_speedster/20344728/20465792/"},"complectation":{"name":"Модификация 5.9 AT","specification":[{"head":"Основные","name":"Объем","value":"5.9 л"},{"head":"Основные","name":"Мощность","value":"390 л.с."},{"head":"Основные","name":"Коробка","value":"автомат"},{"head":"Основные","name":"Тип двигателя","value":"бензин"},{"head":"Основные","name":"Топливо","value":"АИ-95"},{"head":"Основные","name":"Привод","value":"задний"},{"head":"Основные","name":"Разгон","value":"5.4 с"},{"head":"Общая информация","name":"Страна марки","value":"Великобритания"},{"head":"Общая информация","name":"Класс автомобиля","value":"S"},{"head":"Общая информация","name":"Количество дверей","value":"2"},{"head":"Общая информация","name":"Количество мест","value":"2"},{"head":"Размеры, мм","name":"Длина","value":"4674"},{"head":"Размеры, мм","name":"Ширина","value":"1752"},{"head":"Размеры, мм","name":"Высота","value":"1118"},{"head":"Размеры, мм","name":"Колёсная база","value":"2890"},{"head":"Размеры, мм","name":"Клиренс","value":"140"},{"head":"Размеры, мм","name":"Ширина передней колеи","value":"1422"},{"head":"Размеры, мм","name":"Ширина задней колеи","value":"1435"},{"head":"Размеры, мм","name":"Размер колёс","value":"255/55/R17"},{"head":"Объём и масса","name":"Объем багажника мин/макс, л","value":"-"},{"head":"Объём и масса","name":"Объём топливного бака, л","value":"165"},{"head":"Объём и масса","name":"Снаряженная масса, кг","value":"1395"},{"head":"Трансмиссия","name":"Коробка передач","value":"автомат"},{"head":"Трансмиссия","name":"Количество передач","value":"4"},{"head":"Трансмиссия","name":"Тип привода","value":"задний"},{"head":"Подвеска и тормоза","name":"Тип передней подвески","value":"независимая, пружинная"},{"head":"Подвеска и тормоза","name":"Тип задней подвески","value":"независимая, пружинная"},{"head":"Подвеска и тормоза","name":"Передние тормоза","value":"дисковые"},{"head":"Подвеска и тормоза","name":"Задние тормоза","value":"дисковые"},{"head":"Эксплуатационные показатели","name":"Максимальная скорость, км/ч","value":"257"},{"head":"Эксплуатационные показатели","name":"Разгон до 100 км/ч, с","value":"5.4"},{"head":"Эксплуатационные показатели","name":"Марка топлива","value":"АИ-95"},{"head":"Двигатель","name":"Тип двигателя","value":"бензин"},{"head":"Двигатель","name":"Объем двигателя, см³","value":"5900"},{"head":"Двигатель","name":"Тип наддува","value":"нет"},{"head":"Двигатель","name":"Максимальная мощность, л.с./кВт при об/мин","value":"390 / 287 при 5500"},{"head":"Двигатель","name":"Максимальный крутящий момент, Н*м при об/мин","value":"500 при 4000"},{"head":"Двигатель","name":"Расположение цилиндров","value":"V-образное"},{"head":"Двигатель","name":"Количество цилиндров","value":"8"},{"head":"Двигатель","name":"Число клапанов на цилиндр","value":"4"},{"head":"Двигатель","name":"Система питания двигателя","value":"распределенный впрыск (многоточечный)"},{"head":"Двигатель","name":"Степень сжатия","value":"9.25"},{"head":"Двигатель","name":"Диаметр цилиндра и ход поршня, мм","value":"101.6 × 90.93"}],"url":"https://auto.ru/catalog/cars/bristol/blenheim_speedster/20344728/20465792/specifications/20465792__20465826/"}}
{"brand":"Bristol","model":"Fighter","generation":{"name":"","years":"2004 – 2011","url":"https://auto.ru/catalog/cars/bristol/fighter/20344739/20465794/"},"complectation":{"name":"Модификация 8.0 MT","specification":[{"head":"Основные","name":"Объем","value":"8.0 л"},{"head":"Основные","name":"Мощность","value":"532 л.с."},{"head":"Основные","name":"Коробка","value":"механика"},{"head":"Основные","name":"Тип двигателя","value":"бензин"},{"head":"Основные","name":"Топливо","value":"АИ-95"},{"head":"Основные","name":"Привод","value":"задний"},{"head":"Основные","name":"Разгон","value":"4 с"},{"head":"Общая информация","name":"Страна марки","value":"Великобритания"},{"head":"Общая информация","name":"Класс автомобиля","value":"S"},{"head":"Общая информация","name":"Количество дверей","value":"2"},{"head":"Общая информация","name":"Количество мест","value":"2"},{"head":"Размеры, мм","name":"Длина","value":"4420"},{"head":"Размеры, мм","name":"Ширина","value":"1795"},{"head":"Размеры, мм","name":"Высота","value":"1345"},{"head":"Размеры, мм","name":"Колёсная база","value":"2750"},{"head":"Размеры, мм","name":"Клиренс","value":"130"},{"head":"Размеры, мм","name":"Ширина передней колеи","value":"1470"},{"head":"Размеры, мм","name":"Ширина задней колеи","value":"1470"},{"head":"Размеры, мм","name":"Размер колёс","value":"285/40/R18"},{"head":"Объём и масса","name":"Объем багажника мин/макс, л","value":"-"},{"head":"Объём и масса","name":"Объём топливного бака, л","value":"105"},{"head":"Объём и масса","name":"Снаряженная масса, кг","value":"1475"},{"head":"Трансмиссия","name":"Коробка передач","value":"механика"},{"head":"Трансмиссия","name":"Количество передач","value":"6"},{"head":"Трансмиссия","name":"Тип привода","value":"задний"},{"head":"Подвеска и тормоза","name":"Тип передней подвески","value":"независимая, пружинная"},{"head":"Подвеска и тормоза","name":"Тип задней подвески","value":"независимая, пружинная"},{"head":"Подвеска и тормоза","name":"Передние тормоза","value":"дисковые вентилируемые"},{"head":"Подвеска и тормоза","name":"Задние тормоза","value":"дисковые вентилируемые"},{"head":"Эксплуатационные показатели","name":"Максимальная скорость, км/ч","value":"340"},{"head":"Эксплуатационные показатели","name":"Разгон до 100 км/ч, с","value":"4"},{"head":"Эксплуатационные показатели","name":"Расход топлива, л город/трасса","value":"25/12"},{"head":"Эксплуатационные показатели","name":"Марка топлива","value":"АИ-95"},{"head":"Двигатель","name":"Тип двигателя","value":"бензин"},{"head":"Двигатель","name":"Объем двигателя, см³","value":"7996"},{"head":"Двигатель","name":"Тип наддува","value":"нет"},{"head":"Двигатель","name":"Максимальная мощность, л.с./кВт при об/мин","value":"532 / 391 при 5600"},{"head":"Двигатель","name":"Максимальный крутящий момент, Н*м при об/мин","value":"712 при 4200"},{"head":"Двигатель","name":"Расположение цилиндров","value":"V-образное"},{"head":"Двигатель","name":"Количество цилиндров","value":"10"},{"head":"Двигатель","name":"Число клапанов на цилиндр","value":"4"},{"head":"Двигатель","name":"Система питания двигателя","value":"распределенный впрыск (многоточечный)"},{"head":"Двигатель","name":"Степень сжатия","value":"9.25"},{"head":"Двигатель","name":"Диаметр цилиндра и ход поршня, мм","value":"101.6 × 98.6"}],"url":"https://auto.ru/catalog/cars/bristol/fighter/20344739/20465794/specifications/20465794__20465828/"}}
{"brand":"Bristol","model":"Fighter","generation":{"name":"","years":"2004 – 2011","url":"https://auto.ru/catalog/cars/bristol/fighter/20344739/20465794/"},"complectation":{"name":"Модификация 8.0 AT","specification":[{"head":"Основные","name":"Объем","value":"8.0 л"},{"head":"Основные","name":"Мощность","value":"532 л.с."},{"head":"Основные","name":"Коробка","value":"автомат"},{"head":"Основные","name":"Тип двигателя","value":"бензин"},{"head":"Основные","name":"Топливо","value":"АИ-95"},{"head":"Основные","name":"Привод","value":"задний"},{"head":"Общая информация","name":"Страна марки","value":"Великобритания"},{"head":"Общая информация","name":"Класс автомобиля","value":"S"},{"head":"Общая информация","name":"Количество дверей","value":"2"},{"head":"Общая информация","name":"Количество мест","value":"2"},{"head":"Размеры, мм","name":"Длина","value":"4420"},{"head":"Размеры, мм","name":"Ширина","value":"1795"},{"head":"Размеры, мм","name":"Высота","value":"1345"},{"head":"Размеры, мм","name":"Колёсная база","value":"2750"},{"head":"Размеры, мм","name":"Клиренс","value":"130"},{"head":"Размеры, мм","name":"Ширина передней колеи","value":"1470"},{"head":"Размеры, мм","name":"Ширина задней колеи","value":"1470"},{"head":"Размеры, мм","name":"Размер колёс","value":"285/40/R18"},{"head":"Объём и масса","name":"Объем багажника мин/макс, л","value":"-"},{"head":"Объём и масса","name":"Объём топливного бака, л","value":"105"},{"head":"Трансмиссия","name":"Коробка передач","value":"автомат"},{"head":"Трансмиссия","name":"Количество передач","value":"4"},{"head":"Трансмиссия","name":"Тип привода","value":"задний"},{"head":"Подвеска и тормоза","name":"Тип передней подвески","value":"независимая, пружинная"},{"head":"Подвеска и тормоза","name":"Тип задней подвески","value":"независимая, пружинная"},{"head":"Подвеска и тормоза","name":"Передние тормоза","value":"дисковые вентилируемые"},{"head":"Подвеска и тормоза","name":"Задние тормоза","value":"дисковые вентилируемые"},{"head":"Эксплуатационные показатели","name":"Марка топлива","value":"АИ-95"},{"head":"Двигатель","name":"Тип двигателя","value":"бензин"},{"head":"Двигатель","name":"Объем двигателя, см³","value":"7996"},{"head":"Двигатель","name":"Тип наддува","value":"нет"},{"head":"Двигатель","name":"Максимальная мощность, л.с./кВт при об/мин","value":"532 / 391 при 5600"},{"head":"Двигатель","name":"Максимальный крутящий момент, Н*м при об/мин","value":"712 при 4200"},{"head":"Двигатель","name":"Расположение цилиндров","value":"V-образное"},{"head":"Двигатель","name":"Количество цилиндров","value":"10"},{"head":"Двигатель","name":"Число клапанов на цилиндр","value":"4"},{"head":"Двигатель","name":"Система питания двигателя","value":"распределенный впрыск (многоточечный)"},{"head":"Двигатель","name":"Степень сжатия","value":"9.25"},{"head":"Двигатель","name":"Диаметр цилиндра и ход поршня, мм","value":"101.6 × 98.6"}],"url":"https://auto.ru/catalog/cars/bristol/fighter/20344739/20465794/specifications/20465794__20465879/"}}
{"brand":"Bristol","model":"Fighter","generation":{"name":"","years":"2004 – 2011","url":"https://auto.ru/catalog/cars/bristol/fighter/20344739/20465794/"},"complectation":{"name":"Модификация 8.0 MT","specification":[{"head":"Основные","name":"Объем","value":"8.0 л"},{"head":"Основные","name":"Мощность","value":"637 л.с."},{"head":"Основные","name":"Коробка","value":"механика"},{"head":"Основные","name":"Тип двигателя","value":"бензин"},{"head":"Основные","name":"Топливо","value":"АИ-95"},{"head":"Основные","name":"Привод","value":"задний"},{"head":"Основные","name":"Разгон","value":"4 с"},{"head":"Общая информация","name":"Страна марки","value":"Великобритания"},{"head":"Общая информация","name":"Класс автомобиля","value":"S"},{"head":"Общая информация","name":"Количество дверей","value":"2"},{"head":"Общая информация","name":"Количество мест","value":"2"},{"head":"Размеры, мм","name":"Длина","value":"4420"},{"head":"Размеры, мм","name":"Ширина","value":"1795"},{"head":"Размеры, мм","name":"Высота","value":"1345"},{"head":"Размеры, мм","name":"Колёсная база","value":"2750"},{"head":"Размеры, мм","name":"Клиренс","value":"130"},{"head":"Размеры, мм","name":"Ширина передней колеи","value":"1470"},{"head":"Размеры, мм","name":"Ширина задней колеи","value":"1470"},{"head":"Размеры, мм","name":"Размер колёс","value":"285/40/R18"},{"head":"Объём и масса","name":"Объем багажника мин/макс, л","value":"-"},{"head":"Объём и масса","name":"Объём топливного бака, л","value":"105"},{"head":"Объём и масса","name":"Снаряженная масса, кг","value":"1475"},{"head":"Трансмиссия","name":"Коробка передач","value":"механика"},{"head":"Трансмиссия","name":"Количество передач","value":"6"},{"head":"Трансмиссия","name":"Тип привода","value":"задний"},{"head":"Подвеска и тормоза","name":"Тип передней подвески","value":"независимая, пружинная"},{"head":"Подвеска и тормоза","name":"Тип задней подвески","value":"независимая, пружинная"},{"head":"Подвеска и тормоза","name":"Передние тормоза","value":"дисковые вентилируемые"},{"head":"Подвеска и тормоза","name":"Задние тормоза","value":"дисковые вентилируемые"},{"head":"Эксплуатационные показатели","name":"Максимальная скорость, км/ч","value":"340"},{"head":"Эксплуатационные показатели","name":"Разгон до 100 км/ч, с","value":"4"},{"head":"Эксплуатационные показатели","name":"Расход топлива, л город/трасса","value":"25/12"},{"head":"Эксплуатационные показатели","name":"Марка топлива","value":"АИ-95"},{"head":"Двигатель","name":"Тип двигателя","value":"бензин"},{"head":"Двигатель","name":"Объем двигателя, см³","value":"7996"},{"head":"Двигатель","name":"Тип наддува","value":"нет"},{"head":"Двигатель","name":"Максимальная мощность, л.с./кВт при об/мин","value":"637 / 469 при 5900"},{"head":"Двигатель","name":"Максимальный крутящий момент, Н*м при об/мин","value":"790 при 3900"},{"head":"Двигатель","name":"Расположение цилиндров","value":"V-образное"},{"head":"Двигатель","name":"Количество цилиндров","value":"10"},{"head":"Двигатель","name":"Число клапанов на цилиндр","value":"4"},{"head":"Двигатель","name":"Система питания двигателя","value":"распределенный впрыск (многоточечный)"},{"head":"Двигатель","name":"Степень сжатия","value":"9.25"},{"head":"Двигатель","name":"Диаметр цилиндра и ход поршня, мм","value":"101.6 × 98.6"}],"url":"https://auto.ru/catalog/cars/bristol/fighter/20344739/20465794/specifications/20465794__20465850/"}}
{"brand":"Bristol","model":"Fighter","generation":{"name":"","years":"2004 – 2011","url":"https://auto.ru/catalog/cars/bristol/fighter/20344739/20465794/"},"complectation":{"name":"Модификация 8.0 MT","specification":[{"head":"Основные","name":"Объем","value":"8.0 л"},{"head":"Основные","name":"Мощность","value":"1026 л.с."},{"head":"Основные","name":"Коробка","value":"механика"},{"head":"Основные","name":"Тип двигателя","value":"бензин"},{"head":"Основные","name":"Топливо","value":"АИ-95"},{"head":"Основные","name":"Привод","value":"задний"},{"head":"Основные","name":"Разгон","value":"3.5 с"},{"head":"Общая информация","name":"Страна марки","value":"Великобритания"},{"head":"Общая информация","name":"Класс автомобиля","value":"S"},{"head":"Общая информация","name":"Количество дверей","value":"2"},{"head":"Общая информация","name":"Количество мест","value":"2"},{"head":"Размеры, мм","name":"Длина","value":"4420"},{"head":"Размеры, мм","name":"Ширина","value":"1795"},{"head":"Размеры, мм","name":"Высота","value":"1345"},{"head":"Размеры, мм","name":"Колёсная база","value":"2750"},{"head":"Размеры, мм","name":"Клиренс","value":"130"},{"head":"Размеры, мм","name":"Ширина передней колеи","value":"1470"},{"head":"Размеры, мм","name":"Ширина задней колеи","value":"1470"},{"head":"Размеры, мм","name":"Размер колёс","value":"285/40/R18"},{"head":"Объём и масса","name":"Объем багажника мин/макс, л","value":"-"},{"head":"Объём и масса","name":"Объём топливного бака, л","value":"105"},{"head":"Объём и масса","name":"Снаряженная масса, кг","value":"1600"},{"head":"Трансмиссия","name":"Коробка передач","value":"механика"},{"head":"Трансмиссия","name":"Количество передач","value":"6"},{"head":"Трансмиссия","name":"Тип привода","value":"задний"},{"head":"Подвеска и тормоза","name":"Тип передней подвески","value":"независимая, пружинная"},{"head":"Подвеска и тормоза","name":"Тип задней подвески","value":"независимая, пружинная"},{"head":"Подвеска и тормоза","name":"Передние тормоза","value":"дисковые вентилируемые"},{"head":"Подвеска и тормоза","name":"Задние тормоза","value":"дисковые вентилируемые"},{"head":"Эксплуатационные показатели","name":"Максимальная скорость, км/ч","value":"362"},{"head":"Эксплуатационные показатели","name":"Разгон до 100 км/ч, с","value":"3.5"},{"head":"Эксплуатационные показатели","name":"Марка топлива","value":"АИ-95"},{"head":"Двигатель","name":"Тип двигателя","value":"бензин"},{"head":"Двигатель","name":"Объем двигателя, см³","value":"7996"},{"head":"Двигатель","name":"Тип наддува","value":"турбонаддув"},{"head":"Двигатель","name":"Максимальная мощность, л.с./кВт при об/мин","value":"1026 / 755 при 5600"},{"head":"Двигатель","name":"Максимальный крутящий момент, Н*м при об/мин","value":"1405 при 4500"},{"head":"Двигатель","name":"Расположение цилиндров","value":"V-образное"},{"head":"Двигатель","name":"Количество цилиндров","value":"10"},{"head":"Двигатель","name":"Число клапанов на цилиндр","value":"4"},{"head":"Двигатель","name":"Система питания двигателя","value":"распределенный впрыск (многоточечный)"},{"head":"Двигатель","name":"Степень сжатия","value":"9.25"},{"head":"Двигатель","name":"Диаметр цилиндра и ход поршня, мм","value":"101.6 × 98.6"}],"url":"https://auto.ru/catalog/cars/bristol/fighter/20344739/20465794/specifications/20465794__20465866/"}}
