{"brand":"Wiesmann","model":"GT","generation":{"name":"","years":"2003 – 2013","url":"https://auto.ru/catalog/cars/wiesmann/gt/20351465/20475221/"},"complectation":{"name":"Модификация 4.4 AT","specification":[{"head":"Основные","name":"Объем","value":"4.4 л"},{"head":"Основные","name":"Мощность","value":"407 л.с."},{"head":"Основные","name":"Коробка","value":"автомат"},{"head":"Основные","name":"Тип двигателя","value":"бензин"},{"head":"Основные","name":"Топливо","value":"АИ-98"},{"head":"Основные","name":"Привод","value":"задний"},{"head":"Основные","name":"Разгон","value":"4.6 с"},{"head":"Основные","name":"Расход","value":"12.3 л"},{"head":"Общая информация","name":"Страна марки","value":"Германия"},{"head":"Общая информация","name":"Класс автомобиля","value":"S"},{"head":"Общая информация","name":"Количество дверей","value":"2"},{"head":"Общая информация","name":"Количество мест","value":"2"},{"head":"Размеры, мм","name":"Длина","value":"4230"},{"head":"Размеры, мм","name":"Ширина","value":"1850"},{"head":"Размеры, мм","name":"Высота","value":"1190"},{"head":"Размеры, мм","name":"Колёсная база","value":"2507"},{"head":"Размеры, мм","name":"Клиренс","value":"110"},{"head":"Размеры, мм","name":"Ширина передней колеи","value":"1564"},{"head":"Размеры, мм","name":"Ширина задней колеи","value":"1621"},{"head":"Объём и масса","name":"Объем багажника мин/макс, л","value":"-"},{"head":"Объём и масса","name":"Снаряженная масса, кг","value":"1390"},{"head":"Трансмиссия","name":"Коробка передач","value":"автомат"},{"head":"Трансмиссия","name":"Количество передач","value":"6"},{"head":"Трансмиссия","name":"Тип привода","value":"задний"},{"head":"Подвеска и тормоза","name":"Тип передней подвески","value":"независимая, пружинная"},{"head":"Подвеска и тормоза","name":"Тип задней подвески","value":"независимая, пружинная"},{"head":"Подвеска и тормоза","name":"Передние тормоза","value":"дисковые вентилируемые"},{"head":"Подвеска и тормоза","name":"Задние тормоза","value":"дисковые"},{"head":"Эксплуатационные показатели","name":"Максимальная скорость, км/ч","value":"291"},{"head":"Эксплуатационные показатели","name":"Разгон до 100 км/ч, с","value":"4.6"},{"head":"Эксплуатационные показатели","name":"Расход топлива, л город/трасса/смешанный","value":"17.2/9.4/12.3"},{"head":"Эксплуатационные показатели","name":"Марка топлива","value":"АИ-98"},{"head":"Двигатель","name":"Тип двигателя","value":"бензин"},{"head":"Двигатель","name":"Объем двигателя, см³","value":"4395"},{"head":"Двигатель","name":"Тип наддува","value":"турбонаддув"},{"head":"Двигатель","name":"Максимальная мощность, л.с./кВт при об/мин","value":"407 / 299 при 5500"},{"head":"Двигатель","name":"Максимальный крутящий момент, Н*м при об/мин","value":"600 при 1750 – 4500"},{"head":"Двигатель","name":"Расположение цилиндров","value":"V-образное"},{"head":"Двигатель","name":"Количество цилиндров","value":"8"},{"head":"Двигатель","name":"Число клапанов на цилиндр","value":"4"},{"head":"Двигатель","name":"Система питания двигателя","value":"распределенный впрыск (многоточечный)"},{"head":"Двигатель","name":"Степень сжатия","value":"10"},{"head":"Двигатель","name":"Диаметр цилиндра и ход поршня, мм","value":"88.3 × 89"}],"url":"https://auto.ru/catalog/cars/wiesmann/gt/20351465/20475221/specifications/20475221__20475272/"}}
{"brand":"Wiesmann","model":"GT","generation":{"name":"","years":"2003 – 2013","url":"https://auto.ru/catalog/cars/wiesmann/gt/20351465/20475221/"},"complectation":{"name":"Модификация 4.4 AT","specification":[{"head":"Основные","name":"Объем","value":"4.4 л"},{"head":"Основные","name":"Мощность","value":"555 л.с."},{"head":"Основные","name":"Коробка","value":"автомат"},{"head":"Основные","name":"Тип двигателя","value":"бензин"},{"head":"Основные","name":"Топливо","value":"АИ-98"},{"head":"Основные","name":"Привод","value":"задний"},{"head":"Основные","name":"Разгон","value":"3.9 с"},{"head":"Основные","name":"Расход","value":"12.9 л"},{"head":"Общая информация","name":"Страна марки","value":"Германия"},{"head":"Общая информация","name":"Класс автомобиля","value":"S"},{"head":"Общая информация","name":"Количество дверей","value":"2"},{"head":"Общая информация","name":"Количество мест","value":"2"},{"head":"Размеры, мм","name":"Длина","value":"4230"},{"head":"Размеры, мм","name":"Ширина","value":"1850"},{"head":"Размеры, мм","name":"Высота","value":"1190"},{"head":"Размеры, мм","name":"Колёсная база","value":"2507"},{"head":"Размеры, мм","name":"Клиренс","value":"110"},{"head":"Размеры, мм","name":"Ширина передней колеи","value":"1564"},{"head":"Размеры, мм","name":"Ширина задней колеи","value":"1621"},{"head":"Объём и масса","name":"Объем багажника мин/макс, л","value":"-"},{"head":"Объём и масса","name":"Снаряженная масса, кг","value":"1405"},{"head":"Трансмиссия","name":"Коробка передач","value":"автомат"},{"head":"Трансмиссия","name":"Количество передач","value":"6"},{"head":"Трансмиссия","name":"Тип привода","value":"задний"},{"head":"Подвеска и тормоза","name":"Тип передней подвески","value":"независимая, пружинная"},{"head":"Подвеска и тормоза","name":"Тип задней подвески","value":"независимая, пружинная"},{"head":"Подвеска и тормоза","name":"Передние тормоза","value":"дисковые вентилируемые"},{"head":"Подвеска и тормоза","name":"Задние тормоза","value":"дисковые"},{"head":"Эксплуатационные показатели","name":"Максимальная скорость, км/ч","value":"311"},{"head":"Эксплуатационные показатели","name":"Разгон до 100 км/ч, с","value":"3.9"},{"head":"Эксплуатационные показатели","name":"Расход топлива, л город/трасса/смешанный","value":"15.8/7.9/12.9"},{"head":"Эксплуатационные показатели","name":"Марка топлива","value":"АИ-98"},{"head":"Двигатель","name":"Тип двигателя","value":"бензин"},{"head":"Двигатель","name":"Расположение двигателя","value":"переднее, продольное"},{"head":"Двигатель","name":"Объем двигателя, см³","value":"4395"},{"head":"Двигатель","name":"Тип наддува","value":"турбонаддув"},{"head":"Двигатель","name":"Максимальная мощность, л.с./кВт при об/мин","value":"555 / 408 при 6000"},{"head":"Двигатель","name":"Максимальный крутящий момент, Н*м при об/мин","value":"680 при 1750"},{"head":"Двигатель","name":"Расположение цилиндров","value":"V-образное"},{"head":"Двигатель","name":"Количество цилиндров","value":"8"},{"head":"Двигатель","name":"Число клапанов на цилиндр","value":"4"},{"head":"Двигатель","name":"Система питания двигателя","value":"распределенный впрыск (многоточечный)"},{"head":"Двигатель","name":"Диаметр цилиндра и ход поршня, мм","value":"-"}],"url":"https://auto.ru/catalog/cars/wiesmann/gt/20351465/20475221/specifications/20475221__20475284/"}}
{"brand":"Wiesmann","model":"Roadster","generation":{"name":"","years":"1996 – 2013","url":"https://auto.ru/catalog/cars/wiesmann/roadster/20351476/20481598/"},"complectation":{"name":"Модификация 2.8 MT","specification":[{"head":"Основные","name":"Объем","value":"2.8 л"},{"head":"Основные","name":"Мощность","value":"193 л.с."},{"head":"Основные","name":"Коробка","value":"механика"},{"head":"Основные","name":"Тип двигателя","value":"бензин"},{"head":"Основные","name":"Топливо","value":"АИ-95"},{"head":"Основные","name":"Привод","value":"задний"},{"head":"Основные","name":"Разгон","value":"6 с"},{"head":"Основные","name":"Расход","value":"9.2 л"},{"head":"Общая информация","name":"Страна марки","value":"Германия"},{"head":"Общая информация","name":"Класс автомобиля","value":"S"},{"head":"Общая информация","name":"Количество дверей","value":"2"},{"head":"Общая информация","name":"Количество мест","value":"2"},{"head":"Размеры, мм","name":"Длина","value":"3860"},{"head":"Размеры, мм","name":"Ширина","value":"1750"},{"head":"Размеры, мм","name":"Высота","value":"1160"},{"head":"Размеры, мм","name":"Колёсная база","value":"2450"},{"head":"Размеры, мм","name":"Клиренс","value":"110"},{"head":"Размеры, мм","name":"Ширина передней колеи","value":"1450"},{"head":"Размеры, мм","name":"Ширина задней колеи","value":"1520"},{"head":"Размеры, мм","name":"Размер колёс","value":"215/50/R17"},{"head":"Объём и масса","name":"Объем багажника мин/макс, л","value":"-"},{"head":"Объём и масса","name":"Объём топливного бака, л","value":"60"},{"head":"Объём и масса","name":"Снаряженная масса, кг","value":"995"},{"head":"Трансмиссия","name":"Коробка передач","value":"механика"},{"head":"Трансмиссия","name":"Количество передач","value":"5"},{"head":"Трансмиссия","name":"Тип привода","value":"задний"},{"head":"Подвеска и тормоза","name":"Тип передней подвески","value":"независимая, пружинная"},{"head":"Подвеска и тормоза","name":"Тип задней подвески","value":"независимая, пружинная"},{"head":"Подвеска и тормоза","name":"Передние тормоза","value":"дисковые вентилируемые"},{"head":"Подвеска и тормоза","name":"Задние тормоза","value":"дисковые"},{"head":"Эксплуатационные показатели","name":"Максимальная скорость, км/ч","value":"225"},{"head":"Эксплуатационные показатели","name":"Разгон до 100 км/ч, с","value":"6"},{"head":"Эксплуатационные показатели","name":"Расход топлива, л смешанный","value":"9.2"},{"head":"Эксплуатационные показатели","name":"Марка топлива","value":"АИ-95"},{"head":"Двигатель","name":"Тип двигателя","value":"бензин"},{"head":"Двигатель","name":"Объем двигателя, см³","value":"2793"},{"head":"Двигатель","name":"Тип наддува","value":"нет"},{"head":"Двигатель","name":"Максимальная мощность, л.с./кВт при об/мин","value":"193 / 142 при 5300"},{"head":"Двигатель","name":"Максимальный крутящий момент, Н*м при об/мин","value":"280 при 3950"},{"head":"Двигатель","name":"Расположение цилиндров","value":"рядное"},{"head":"Двигатель","name":"Количество цилиндров","value":"6"},{"head":"Двигатель","name":"Число клапанов на цилиндр","value":"4"},{"head":"Двигатель","name":"Система питания двигателя","value":"распределенный впрыск (многоточечный)"},{"head":"Двигатель","name":"Степень сжатия","value":"10.2"},{"head":"Двигатель","name":"Диаметр цилиндра и ход поршня, мм","value":"84 × 84"}],"url":"https://auto.ru/catalog/cars/wiesmann/roadster/20351476/20481598/specifications/20481598__20481651/"}}
{"brand":"Wiesmann","model":"Roadster","generation":{"name":"","years":"1996 – 2013","url":"https://auto.ru/catalog/cars/wiesmann/roadster/20351476/20481598/"},"complectation":{"name":"Модификация 3.0 MT","specification":[{"head":"Основные","name":"Объем","value":"3.0 л"},{"head":"Основные","name":"Мощность","value":"231 л.с."},{"head":"Основные","name":"Коробка","value":"механика"},{"head":"Основные","name":"Тип двигателя","value":"бензин"},{"head":"Основные","name":"Топливо","value":"АИ-95"},{"head":"Основные","name":"Привод","value":"задний"},{"head":"Основные","name":"Разгон","value":"5.9 с"},{"head":"Основные","name":"Расход","value":"10 л"},{"head":"Общая информация","name":"Страна марки","value":"Германия"},{"head":"Общая информация","name":"Класс автомобиля","value":"S"},{"head":"Общая информация","name":"Количество дверей","value":"2"},{"head":"Общая информация","name":"Количество мест","value":"2"},{"head":"Размеры, мм","name":"Длина","value":"3860"},{"head":"Размеры, мм","name":"Ширина","value":"1750"},{"head":"Размеры, мм","name":"Высота","value":"1160"},{"head":"Размеры, мм","name":"Колёсная база","value":"2450"},{"head":"Размеры, мм","name":"Клиренс","value":"110"},{"head":"Размеры, мм","name":"Ширина передней колеи","value":"1450"},{"head":"Размеры, мм","name":"Ширина задней колеи","value":"1520"},{"head":"Размеры, мм","name":"Размер колёс","value":"215/50/R17"},{"head":"Объём и масса","name":"Объем багажника мин/макс, л","value":"-"},{"head":"Объём и масса","name":"Объём топливного бака, л","value":"60"},{"head":"Объём и масса","name":"Снаряженная масса, кг","value":"1080"},{"head":"Объём и масса","name":"Полная масса, кг","value":"1400"},{"head":"Трансмиссия","name":"Коробка передач","value":"механика"},{"head":"Трансмиссия","name":"Количество передач","value":"5"},{"head":"Трансмиссия","name":"Тип привода","value":"задний"},{"head":"Подвеска и тормоза","name":"Тип передней подвески","value":"независимая, пружинная"},{"head":"Подвеска и тормоза","name":"Тип задней подвески","value":"независимая, пружинная"},{"head":"Подвеска и тормоза","name":"Передние тормоза","value":"дисковые вентилируемые"},{"head":"Подвеска и тормоза","name":"Задние тормоза","value":"дисковые"},{"head":"Эксплуатационные показатели","name":"Максимальная скорость, км/ч","value":"230"},{"head":"Эксплуатационные показатели","name":"Разгон до 100 км/ч, с","value":"5.9"},{"head":"Эксплуатационные показатели","name":"Расход топлива, л смешанный","value":"10"},{"head":"Эксплуатационные показатели","name":"Марка топлива","value":"АИ-95"},{"head":"Двигатель","name":"Тип двигателя","value":"бензин"},{"head":"Двигатель","name":"Объем двигателя, см³","value":"2979"},{"head":"Двигатель","name":"Тип наддува","value":"нет"},{"head":"Двигатель","name":"Максимальная мощность, л.с./кВт при об/мин","value":"231 / 170 при 5900"},{"head":"Двигатель","name":"Максимальный крутящий момент, Н*м при об/мин","value":"300 при 3500"},{"head":"Двигатель","name":"Расположение цилиндров","value":"рядное"},{"head":"Двигатель","name":"Количество цилиндров","value":"6"},{"head":"Двигатель","name":"Число клапанов на цилиндр","value":"4"},{"head":"Двигатель","name":"Система питания двигателя","value":"распределенный впрыск (многоточечный)"},{"head":"Двигатель","name":"Степень сжатия","value":"10.2"},{"head":"Двигатель","name":"Диаметр цилиндра и ход поршня, мм","value":"84 × 89.6"}],"url":"https://auto.ru/catalog/cars/wiesmann/roadster/20351476/20481598/specifications/20481598__20481669/"}}
{"brand":"Wiesmann","model":"Roadster","generation":{"name":"","years":"1996 – 2013","url":"https://auto.ru/catalog/cars/wiesmann/roadster/20351476/20481598/"},"complectation":{"name":"Модификация 3.2 MT","specification":[{"head":"Основные","name":"Объем","value":"3.2 л"},{"head":"Основные","name":"Мощность","value":"321 л.с."},{"head":"Основные","name":"Коробка","value":"механика"},{"head":"Основные","name":"Тип двигателя","value":"бензин"},{"head":"Основные","name":"Топливо","value":"АИ-98"},{"head":"Основные","name":"Привод","value":"задний"},{"head":"Основные","name":"Разгон","value":"4.9 с"},{"head":"Основные","name":"Расход","value":"11 л"},{"head":"Общая информация","name":"Страна марки","value":"Германия"},{"head":"Общая информация","name":"Класс автомобиля","value":"S"},{"head":"Общая информация","name":"Количество дверей","value":"2"},{"head":"Общая информация","name":"Количество мест","value":"2"},{"head":"Размеры, мм","name":"Длина","value":"3860"},{"head":"Размеры, мм","name":"Ширина","value":"1750"},{"head":"Размеры, мм","name":"Высота","value":"1160"},{"head":"Размеры, мм","name":"Колёсная база","value":"2450"},{"head":"Размеры, мм","name":"Клиренс","value":"110"},{"head":"Размеры, мм","name":"Ширина передней колеи","value":"1450"},{"head":"Размеры, мм","name":"Ширина задней колеи","value":"1520"},{"head":"Размеры, мм","name":"Размер колёс","value":"215/50/R17"},{"head":"Объём и масса","name":"Объем багажника мин/макс, л","value":"-"},{"head":"Объём и масса","name":"Объём топливного бака, л","value":"60"},{"head":"Объём и масса","name":"Снаряженная масса, кг","value":"1060"},{"head":"Трансмиссия","name":"Коробка передач","value":"механика"},{"head":"Трансмиссия","name":"Количество передач","value":"6"},{"head":"Трансмиссия","name":"Тип привода","value":"задний"},{"head":"Подвеска и тормоза","name":"Тип передней подвески","value":"независимая, пружинная"},{"head":"Подвеска и тормоза","name":"Тип задней подвески","value":"независимая, пружинная"},{"head":"Подвеска и тормоза","name":"Передние тормоза","value":"дисковые вентилируемые"},{"head":"Подвеска и тормоза","name":"Задние тормоза","value":"дисковые"},{"head":"Эксплуатационные показатели","name":"Максимальная скорость, км/ч","value":"255"},{"head":"Эксплуатационные показатели","name":"Разгон до 100 км/ч, с","value":"4.9"},{"head":"Эксплуатационные показатели","name":"Расход топлива, л смешанный","value":"11"},{"head":"Эксплуатационные показатели","name":"Марка топлива","value":"АИ-98"},{"head":"Двигатель","name":"Тип двигателя","value":"бензин"},{"head":"Двигатель","name":"Объем двигателя, см³","value":"3201"},{"head":"Двигатель","name":"Тип наддува","value":"нет"},{"head":"Двигатель","name":"Максимальная мощность, л.с./кВт при об/мин","value":"321 / 236 при 7400"},{"head":"Двигатель","name":"Максимальный крутящий момент, Н*м при об/мин","value":"350 при 3250"},{"head":"Двигатель","name":"Расположение цилиндров","value":"рядное"},{"head":"Двигатель","name":"Количество цилиндров","value":"6"},{"head":"Двигатель","name":"Число клапанов на цилиндр","value":"4"},{"head":"Двигатель","name":"Система питания двигателя","value":"распределенный впрыск (многоточечный)"},{"head":"Двигатель","name":"Степень сжатия","value":"11.3"},{"head":"Двигатель","name":"Диаметр цилиндра и ход поршня, мм","value":"86.4 × 91"}],"url":"https://auto.ru/catalog/cars/wiesmann/roadster/20351476/20481598/specifications/20481598__20481655/"}}
{"brand":"Wiesmann","model":"Roadster","generation":{"name":"","years":"1996 – 2013","url":"https://auto.ru/catalog/cars/wiesmann/roadster/20351476/20481598/"},"complectation":{"name":"Модификация 3.3 MT","specification":[{"head":"Основные","name":"Объем","value":"3.3 л"},{"head":"Основные","name":"Мощность","value":"325 л.с."},{"head":"Основные","name":"Коробка","value":"механика"},{"head":"Основные","name":"Тип двигателя","value":"бензин"},{"head":"Основные","name":"Топливо","value":"АИ-95"},{"head":"Основные","name":"Привод","value":"задний"},{"head":"Основные","name":"Разгон","value":"4.9 с"},{"head":"Основные","name":"Расход","value":"11 л"},{"head":"Общая информация","name":"Страна марки","value":"Германия"},{"head":"Общая информация","name":"Класс автомобиля","value":"S"},{"head":"Общая информация","name":"Количество дверей","value":"2"},{"head":"Общая информация","name":"Количество мест","value":"2"},{"head":"Размеры, мм","name":"Длина","value":"3860"},{"head":"Размеры, мм","name":"Ширина","value":"1750"},{"head":"Размеры, мм","name":"Высота","value":"1160"},{"head":"Размеры, мм","name":"Колёсная база","value":"2450"},{"head":"Размеры, мм","name":"Клиренс","value":"110"},{"head":"Размеры, мм","name":"Ширина передней колеи","value":"1450"},{"head":"Размеры, мм","name":"Ширина задней колеи","value":"1520"},{"head":"Размеры, мм","name":"Размер колёс","value":"215/50/R17"},{"head":"Объём и масса","name":"Объем багажника мин/макс, л","value":"-"},{"head":"Объём и масса","name":"Объём топливного бака, л","value":"60"},{"head":"Объём и масса","name":"Снаряженная масса, кг","value":"1180"},{"head":"Трансмиссия","name":"Коробка передач","value":"механика"},{"head":"Трансмиссия","name":"Количество передач","value":"6"},{"head":"Трансмиссия","name":"Тип привода","value":"задний"},{"head":"Подвеска и тормоза","name":"Тип передней подвески","value":"независимая, пружинная"},{"head":"Подвеска и тормоза","name":"Тип задней подвески","value":"независимая, пружинная"},{"head":"Подвеска и тормоза","name":"Передние тормоза","value":"дисковые вентилируемые"},{"head":"Подвеска и тормоза","name":"Задние тормоза","value":"дисковые"},{"head":"Эксплуатационные показатели","name":"Максимальная скорость, км/ч","value":"255"},{"head":"Эксплуатационные показатели","name":"Разгон до 100 км/ч, с","value":"4.9"},{"head":"Эксплуатационные показатели","name":"Расход топлива, л смешанный","value":"11"},{"head":"Эксплуатационные показатели","name":"Марка топлива","value":"АИ-95"},{"head":"Двигатель","name":"Тип двигателя","value":"бензин"},{"head":"Двигатель","name":"Объем двигателя, см³","value":"3246"},{"head":"Двигатель","name":"Тип наддува","value":"нет"},{"head":"Двигатель","name":"Максимальная мощность, л.с./кВт при об/мин","value":"325 / 239 при 7400"},{"head":"Двигатель","name":"Максимальный крутящий момент, Н*м при об/мин","value":"350 при 4900"},{"head":"Двигатель","name":"Расположение цилиндров","value":"рядное"},{"head":"Двигатель","name":"Количество цилиндров","value":"6"},{"head":"Двигатель","name":"Число клапанов на цилиндр","value":"4"},{"head":"Двигатель","name":"Система питания двигателя","value":"распределенный впрыск (многоточечный)"},{"head":"Двигатель","name":"Степень сжатия","value":"11.5"},{"head":"Двигатель","name":"Диаметр цилиндра и ход поршня, мм","value":"87 × 91"}],"url":"https://auto.ru/catalog/cars/wiesmann/roadster/20351476/20481598/specifications/20481598__20481662/"}}
